Workbook

Sheet Profit & Loss
A1: Historical teaching fixture | Profit & Loss
A2: USD million · Other units shown in row labels · Blank = unavailable · Reported annual figures
A3: Select a value for its SEC filing; its cell note records the original label, tag, unit and filing date.
A4: Line item | B4: 2021-12-31 | C4: 2022-12-31 | D4: 2023-12-31 | E4: 2024-12-31
A5: Revenues | B5: 800 | C5: 900 | D5: 1000 | E5: 1200
A6: CostOfRevenue | B6: 500 | C6: 550 | D6: 600 | E6: 700
A7: GrossProfit | B7: 300 | C7: 350 | D7: 400 | E7: 500
A8: OperatingIncomeLoss | B8: 80 | C8: 90 | D8: 100 | E8: 180
A9: ProfitLoss | B9: 60 | C9: 70 | D9: 80 | E9: 120
A10: NetIncomeLoss | B10: 58 | C10: 68 | D10: 78 | E10: 118
A11: NetIncomeLossAvailableToCommonStockholdersBasic | B11: 58 | C11: 68 | D11: 78 | E11: 118
A12: InterestExpense | B12: 10 | C12: 10 | D12: 10 | E12: 12
A13: IncomeLossFromContinuingOperationsBeforeIncomeTaxesExtraordinaryItemsNoncontrollingInterest | B13: 75 | C13: 87.5 | D13: 100 | E13: 150
A14: IncomeTaxExpenseBenefit | B14: 15 | C14: 17.5 | D14: 20 | E14: 30
A15: CommonStockDividendsPerShareDeclared (USD/shares) | B15: 0.1 | C15: 0.12 | D15: 0.15 | E15: 0.25
A16: EarningsPerShareBasic (USD/shares) | B16: 0.58 | C16: 0.68 | D16: 0.78 | E16: 1.475
... A18: WeightedAverageNumberOfDilutedSharesOutstanding (shares) | B18: 100000000 | C18: 100000000 | D18: 100000000 | E18: 80000000

Sheet Balance Sheet
A1: Historical teaching fixture | Balance Sheet
A2: USD million · Other units shown in row labels · Blank = unavailable · Reported annual figures
A3: Select a value for its SEC filing; its cell note records the original label, tag, unit and filing date.
A4: Line item | B4: 2021-12-31 | C4: 2022-12-31 | D4: 2023-12-31 | E4: 2024-12-31
A5: Assets | B5: 800 | C5: 900 | D5: 1100 | E5: 1300
A6: LiabilitiesAndStockholdersEquity | B6: 800 | C6: 900 | D6: 1100 | E6: 1300
A7: AssetsCurrent | B7: 250 | C7: 300 | D7: 350 | E7: 400
A8: LiabilitiesCurrent | B8: 100 | C8: 120 | D8: 140 | E8: 160
A9: CashAndCashEquivalentsAtCarryingValue | B9: 40 | C9: 45 | D9: 50 | E9: 60
A10: ShortTermInvestments | B10: 10 | C10: 12 | D10: 15 | E10: 20
A11: AccountsReceivableNetCurrent | B11: 70 | C11: 80 | D11: 90 | E11: 110
A12: InventoryNet | B12: 100 | C12: 110 | D12: 120 | E12: 160
A13: AccountsPayableCurrent | B13: 50 | C13: 60 | D13: 70 | E13: 90
A14: CommonStockholdersEquity | B14: 400 | C14: 450 | D14: 500 | E14: 600
A15: DebtAndCapitalLeaseObligations | B15: 100 | C15: 120 | D15: 150 | E15: 180
A16: StockholdersEquityIncludingPortionAttributableToNoncontrollingInterest | B16: 410 | C16: 460 | D16: 510 | E16: 620

Sheet Cash Flow
A1: Historical teaching fixture | Cash Flow
A2: USD million · Other units shown in row labels · Blank = unavailable · Reported annual figures
A3: Cash Flow Detail contains every reported cash-flow row. Values here are reported totals, not calculated estimates.
A4: Line item | B4: 2021-12-31 | C4: 2022-12-31 | D4: 2023-12-31 | E4: 2024-12-31
A5: NetCashProvidedByUsedInOperatingActivities | B5: 90 | C5: 100 | D5: 110 | E5: 150

Sheet Cash Flow Detail
A1: Historical teaching fixture | Cash Flow Detail
A2: USD million · Other units shown in row labels · Blank = unavailable · Reported annual figures
A3: Select a value for its SEC filing; its cell note records the original label, tag, unit and filing date.
A4: Line item | B4: 2021-12-31 | C4: 2022-12-31 | D4: 2023-12-31 | E4: 2024-12-31
A5: NetCashProvidedByUsedInOperatingActivities | B5: 90 | C5: 100 | D5: 110 | E5: 150
A6: PaymentsToAcquirePropertyPlantAndEquipment | B6: 30 | C6: 40 | D6: 45 | E6: 50
A7: DepreciationDepletionAndAmortization | B7: 20 | C7: 22 | D7: 25 | E7: 30
A8: PaymentsOfDividendsCommonStock | B8: 10 | C8: 12 | D8: 15 | E8: 20
A9: PaymentsForRepurchaseOfCommonStock | B9: 20 | C9: 25 | D9: 30 | E9: 40

Sheet Data Sheet
A1: Historical teaching fixture | Data Sheet
A2: Latest 20 fiscal periods maximum · USD million · Other units shown in row labels · Blank = unavailable · Reported annual figures
A3: Selected annual statements in one matrix. Select a value for its SEC source and cell note. Full original records: Source Data.
A4: Profit & Loss
A5: Reported line item | B5: 2021-12-31 | C5: 2022-12-31 | D5: 2023-12-31 | E5: 2024-12-31
A6: Revenues | B6: 800 | C6: 900 | D6: 1000 | E6: 1200
A7: CostOfRevenue | B7: 500 | C7: 550 | D7: 600 | E7: 700
A8: GrossProfit | B8: 300 | C8: 350 | D8: 400 | E8: 500
A9: OperatingIncomeLoss | B9: 80 | C9: 90 | D9: 100 | E9: 180
A10: ProfitLoss | B10: 60 | C10: 70 | D10: 80 | E10: 120
A11: NetIncomeLoss | B11: 58 | C11: 68 | D11: 78 | E11: 118
A12: NetIncomeLossAvailableToCommonStockholdersBasic | B12: 58 | C12: 68 | D12: 78 | E12: 118
A13: InterestExpense | B13: 10 | C13: 10 | D13: 10 | E13: 12
A14: IncomeLossFromContinuingOperationsBeforeIncomeTaxesExtraordinaryItemsNoncontrollingInterest | B14: 75 | C14: 87.5 | D14: 100 | E14: 150
A15: IncomeTaxExpenseBenefit | B15: 15 | C15: 17.5 | D15: 20 | E15: 30
A16: CommonStockDividendsPerShareDeclared (USD/shares) | B16: 0.1 | C16: 0.12 | D16: 0.15 | E16: 0.25
A17: EarningsPerShareBasic (USD/shares) | B17: 0.58 | C17: 0.68 | D17: 0.78 | E17: 1.475
... A19: WeightedAverageNumberOfDilutedSharesOutstanding (shares) | B19: 100000000 | C19: 100000000 | D19: 100000000 | E19: 80000000
A21: Balance Sheet
A22: Reported line item | B22: 2021-12-31 | C22: 2022-12-31 | D22: 2023-12-31 | E22: 2024-12-31
A23: Assets | B23: 800 | C23: 900 | D23: 1100 | E23: 1300
A24: LiabilitiesAndStockholdersEquity | B24: 800 | C24: 900 | D24: 1100 | E24: 1300
A25: AssetsCurrent | B25: 250 | C25: 300 | D25: 350 | E25: 400
A26: LiabilitiesCurrent | B26: 100 | C26: 120 | D26: 140 | E26: 160
A27: CashAndCashEquivalentsAtCarryingValue | B27: 40 | C27: 45 | D27: 50 | E27: 60
A28: ShortTermInvestments | B28: 10 | C28: 12 | D28: 15 | E28: 20
A29: AccountsReceivableNetCurrent | B29: 70 | C29: 80 | D29: 90 | E29: 110
A30: InventoryNet | B30: 100 | C30: 110 | D30: 120 | E30: 160
A31: AccountsPayableCurrent | B31: 50 | C31: 60 | D31: 70 | E31: 90
A32: CommonStockholdersEquity | B32: 400 | C32: 450 | D32: 500 | E32: 600
A33: DebtAndCapitalLeaseObligations | B33: 100 | C33: 120 | D33: 150 | E33: 180
A34: StockholdersEquityIncludingPortionAttributableToNoncontrollingInterest | B34: 410 | C34: 460 | D34: 510 | E34: 620
A36: Cash Flow
A37: Reported line item | B37: 2021-12-31 | C37: 2022-12-31 | D37: 2023-12-31 | E37: 2024-12-31
A38: NetCashProvidedByUsedInOperatingActivities | B38: 90 | C38: 100 | D38: 110 | E38: 150
A39: PaymentsToAcquirePropertyPlantAndEquipment | B39: 30 | C39: 40 | D39: 45 | E39: 50
A40: DepreciationDepletionAndAmortization | B40: 20 | C40: 22 | D40: 25 | E40: 30
A41: PaymentsOfDividendsCommonStock | B41: 10 | C41: 12 | D41: 15 | E41: 20
A42: PaymentsForRepurchaseOfCommonStock | B42: 20 | C42: 25 | D42: 30 | E42: 40

Sheet Source Data
A1: Historical teaching fixture | Source Data
A2: Raw source values and optional statement presentation values retain their reported units. Original instant contexts are separate from annual display periods. No monetary scaling or currency conversion is applied on this sheet.
A4: Statement | B4: SEC tag / row identifier | C4: Reported label | D4: Reported unit | E4: Source/XBRL value (unscaled) | F4: Annual display period start | G4: Annual display period end | H4: Accession | I4: Filed | J4: Form | K4: Extraction | L4: Selection reason | M4: Source filing | N4: Displayed cells | O4: Statement presentation value (unscaled) | P4: Original source instant | Q4: Row role | R4: Reported section | S4: Context | T4: Dimensions | U4: Decimals
A5: Profit & Loss | B5: us-gaap:Revenues | C5: Revenues | D5: USD | E5: 800000000 | F5: 2021-01-01 | G5: 2021-12-31 | H5: 0000000001-21-000001 | I5: 2022-02-01 | J5: 10-K | K5: companyfacts | M5: https://www.sec.gov/Archives/edgar/data/1/000000000121000001/annual.htm | N5: 'Profit & Loss'!B5; 'Data Sheet'!B6 | U5: -3
A6: Profit & Loss | B6: us-gaap:Revenues | C6: Revenues | D6: USD | E6: 900000000 | F6: 2022-01-01 | G6: 2022-12-31 | H6: 0000000001-22-000001 | I6: 2023-02-01 | J6: 10-K | K6: companyfacts | M6: https://www.sec.gov/Archives/edgar/data/1/000000000122000001/annual.htm | N6: 'Profit & Loss'!C5; 'Data Sheet'!C6 | U6: -3
A7: Profit & Loss | B7: us-gaap:Revenues | C7: Revenues | D7: USD | E7: 1000000000 | F7: 2023-01-01 | G7: 2023-12-31 | H7: 0000000001-23-000001 | I7: 2024-02-01 | J7: 10-K | K7: companyfacts | M7: https://www.sec.gov/Archives/edgar/data/1/000000000123000001/annual.htm | N7: 'Profit & Loss'!D5; 'Data Sheet'!D6 | U7: -3
A8: Profit & Loss | B8: us-gaap:Revenues | C8: Revenues | D8: USD | E8: 1200000000 | F8: 2024-01-01 | G8: 2024-12-31 | H8: 0000000001-24-000001 | I8: 2025-02-01 | J8: 10-K | K8: companyfacts | M8: https://www.sec.gov/Archives/edgar/data/1/000000000124000001/annual.htm | N8: 'Profit & Loss'!E5; 'Data Sheet'!E6 | U8: -3
A9: Profit & Loss | B9: us-gaap:CostOfRevenue | C9: CostOfRevenue | D9: USD | E9: 500000000 | F9: 2021-01-01 | G9: 2021-12-31 | H9: 0000000001-21-000001 | I9: 2022-02-01 | J9: 10-K | K9: companyfacts | M9: https://www.sec.gov/Archives/edgar/data/1/000000000121000001/annual.htm | N9: 'Profit & Loss'!B6; 'Data Sheet'!B7 | U9: -3
A10: Profit & Loss | B10: us-gaap:CostOfRevenue | C10: CostOfRevenue | D10: USD | E10: 550000000 | F10: 2022-01-01 | G10: 2022-12-31 | H10: 0000000001-22-000001 | I10: 2023-02-01 | J10: 10-K | K10: companyfacts | M10: https://www.sec.gov/Archives/edgar/data/1/000000000122000001/annual.htm | N10: 'Profit & Loss'!C6; 'Data Sheet'!C7 | U10: -3
A11: Profit & Loss | B11: us-gaap:CostOfRevenue | C11: CostOfRevenue | D11: USD | E11: 600000000 | F11: 2023-01-01 | G11: 2023-12-31 | H11: 0000000001-23-000001 | I11: 2024-02-01 | J11: 10-K | K11: companyfacts | M11: https://www.sec.gov/Archives/edgar/data/1/000000000123000001/annual.htm | N11: 'Profit & Loss'!D6; 'Data Sheet'!D7 | U11: -3
A12: Profit & Loss | B12: us-gaap:CostOfRevenue | C12: CostOfRevenue | D12: USD | E12: 700000000 | F12: 2024-01-01 | G12: 2024-12-31 | H12: 0000000001-24-000001 | I12: 2025-02-01 | J12: 10-K | K12: companyfacts | M12: https://www.sec.gov/Archives/edgar/data/1/000000000124000001/annual.htm | N12: 'Profit & Loss'!E6; 'Data Sheet'!E7 | U12: -3
A13: Profit & Loss | B13: us-gaap:GrossProfit | C13: GrossProfit | D13: USD | E13: 300000000 | F13: 2021-01-01 | G13: 2021-12-31 | H13: 0000000001-21-000001 | I13: 2022-02-01 | J13: 10-K | K13: companyfacts | M13: https://www.sec.gov/Archives/edgar/data/1/000000000121000001/annual.htm | N13: 'Profit & Loss'!B7; 'Data Sheet'!B8 | U13: -3
A14: Profit & Loss | B14: us-gaap:GrossProfit | C14: GrossProfit | D14: USD | E14: 350000000 | F14: 2022-01-01 | G14: 2022-12-31 | H14: 0000000001-22-000001 | I14: 2023-02-01 | J14: 10-K | K14: companyfacts | M14: https://www.sec.gov/Archives/edgar/data/1/000000000122000001/annual.htm | N14: 'Profit & Loss'!C7; 'Data Sheet'!C8 | U14: -3
A15: Profit & Loss | B15: us-gaap:GrossProfit | C15: GrossProfit | D15: USD | E15: 400000000 | F15: 2023-01-01 | G15: 2023-12-31 | H15: 0000000001-23-000001 | I15: 2024-02-01 | J15: 10-K | K15: companyfacts | M15: https://www.sec.gov/Archives/edgar/data/1/000000000123000001/annual.htm | N15: 'Profit & Loss'!D7; 'Data Sheet'!D8 | U15: -3
A16: Profit & Loss | B16: us-gaap:GrossProfit | C16: GrossProfit | D16: USD | E16: 500000000 | F16: 2024-01-01 | G16: 2024-12-31 | H16: 0000000001-24-000001 | I16: 2025-02-01 | J16: 10-K | K16: companyfacts | M16: https://www.sec.gov/Archives/edgar/data/1/000000000124000001/annual.htm | N16: 'Profit & Loss'!E7; 'Data Sheet'!E8 | U16: -3
... A36: Profit & Loss | B36: us-gaap:InterestExpense | C36: InterestExpense | D36: USD | E36: 12000000 | F36: 2024-01-01 | G36: 2024-12-31 | H36: 0000000001-24-000001 | I36: 2025-02-01 | J36: 10-K | K36: companyfacts | M36: https://www.sec.gov/Archives/edgar/data/1/000000000124000001/annual.htm | N36: 'Profit & Loss'!E12; 'Data Sheet'!E13 | U36: -3
A37: Balance Sheet | B37: us-gaap:Assets | C37: Assets | D37: USD | E37: 800000000 | G37: 2021-12-31 | H37: 0000000001-21-000001 | I37: 2022-02-01 | J37: 10-K | K37: companyfacts | M37: https://www.sec.gov/Archives/edgar/data/1/000000000121000001/annual.htm | N37: 'Balance Sheet'!B5; 'Data Sheet'!B23 | U37: -3
A38: Balance Sheet | B38: us-gaap:Assets | C38: Assets | D38: USD | E38: 900000000 | G38: 2022-12-31 | H38: 0000000001-22-000001 | I38: 2023-02-01 | J38: 10-K | K38: companyfacts | M38: https://www.sec.gov/Archives/edgar/data/1/000000000122000001/annual.htm | N38: 'Balance Sheet'!C5; 'Data Sheet'!C23 | U38: -3
A39: Balance Sheet | B39: us-gaap:Assets | C39: Assets | D39: USD | E39: 1100000000 | G39: 2023-12-31 | H39: 0000000001-23-000001 | I39: 2024-02-01 | J39: 10-K | K39: companyfacts | M39: https://www.sec.gov/Archives/edgar/data/1/000000000123000001/annual.htm | N39: 'Balance Sheet'!D5; 'Data Sheet'!D23 | U39: -3
A40: Balance Sheet | B40: us-gaap:Assets | C40: Assets | D40: USD | E40: 1300000000 | G40: 2024-12-31 | H40: 0000000001-24-000001 | I40: 2025-02-01 | J40: 10-K | K40: companyfacts | M40: https://www.sec.gov/Archives/edgar/data/1/000000000124000001/annual.htm | N40: 'Balance Sheet'!E5; 'Data Sheet'!E23 | U40: -3
A41: Balance Sheet | B41: us-gaap:LiabilitiesAndStockholdersEquity | C41: LiabilitiesAndStockholdersEquity | D41: USD | E41: 800000000 | G41: 2021-12-31 | H41: 0000000001-21-000001 | I41: 2022-02-01 | J41: 10-K | K41: companyfacts | M41: https://www.sec.gov/Archives/edgar/data/1/000000000121000001/annual.htm | N41: 'Balance Sheet'!B6; 'Data Sheet'!B24 | U41: -3
A42: Balance Sheet | B42: us-gaap:LiabilitiesAndStockholdersEquity | C42: LiabilitiesAndStockholdersEquity | D42: USD | E42: 900000000 | G42: 2022-12-31 | H42: 0000000001-22-000001 | I42: 2023-02-01 | J42: 10-K | K42: companyfacts | M42: https://www.sec.gov/Archives/edgar/data/1/000000000122000001/annual.htm | N42: 'Balance Sheet'!C6; 'Data Sheet'!C24 | U42: -3
A43: Balance Sheet | B43: us-gaap:LiabilitiesAndStockholdersEquity | C43: LiabilitiesAndStockholdersEquity | D43: USD | E43: 1100000000 | G43: 2023-12-31 | H43: 0000000001-23-000001 | I43: 2024-02-01 | J43: 10-K | K43: companyfacts | M43: https://www.sec.gov/Archives/edgar/data/1/000000000123000001/annual.htm | N43: 'Balance Sheet'!D6; 'Data Sheet'!D24 | U43: -3
A44: Balance Sheet | B44: us-gaap:LiabilitiesAndStockholdersEquity | C44: LiabilitiesAndStockholdersEquity | D44: USD | E44: 1300000000 | G44: 2024-12-31 | H44: 0000000001-24-000001 | I44: 2025-02-01 | J44: 10-K | K44: companyfacts | M44: https://www.sec.gov/Archives/edgar/data/1/000000000124000001/annual.htm | N44: 'Balance Sheet'!E6; 'Data Sheet'!E24 | U44: -3
A45: Balance Sheet | B45: us-gaap:AssetsCurrent | C45: AssetsCurrent | D45: USD | E45: 250000000 | G45: 2021-12-31 | H45: 0000000001-21-000001 | I45: 2022-02-01 | J45: 10-K | K45: companyfacts | M45: https://www.sec.gov/Archives/edgar/data/1/000000000121000001/annual.htm | N45: 'Balance Sheet'!B7; 'Data Sheet'!B25 | U45: -3
A46: Balance Sheet | B46: us-gaap:AssetsCurrent | C46: AssetsCurrent | D46: USD | E46: 300000000 | G46: 2022-12-31 | H46: 0000000001-22-000001 | I46: 2023-02-01 | J46: 10-K | K46: companyfacts | M46: https://www.sec.gov/Archives/edgar/data/1/000000000122000001/annual.htm | N46: 'Balance Sheet'!C7; 'Data Sheet'!C25 | U46: -3
A47: Balance Sheet | B47: us-gaap:AssetsCurrent | C47: AssetsCurrent | D47: USD | E47: 350000000 | G47: 2023-12-31 | H47: 0000000001-23-000001 | I47: 2024-02-01 | J47: 10-K | K47: companyfacts | M47: https://www.sec.gov/Archives/edgar/data/1/000000000123000001/annual.htm | N47: 'Balance Sheet'!D7; 'Data Sheet'!D25 | U47: -3
A48: Balance Sheet | B48: us-gaap:AssetsCurrent | C48: AssetsCurrent | D48: USD | E48: 400000000 | G48: 2024-12-31 | H48: 0000000001-24-000001 | I48: 2025-02-01 | J48: 10-K | K48: companyfacts | M48: https://www.sec.gov/Archives/edgar/data/1/000000000124000001/annual.htm | N48: 'Balance Sheet'!E7; 'Data Sheet'!E25 | U48: -3
... A80: Balance Sheet | B80: us-gaap:DebtAndCapitalLeaseObligations | C80: DebtAndCapitalLeaseObligations | D80: USD | E80: 180000000 | G80: 2024-12-31 | H80: 0000000001-24-000001 | I80: 2025-02-01 | J80: 10-K | K80: companyfacts | M80: https://www.sec.gov/Archives/edgar/data/1/000000000124000001/annual.htm | N80: 'Balance Sheet'!E15; 'Data Sheet'!E33 | U80: -3
A81: Cash Flow | B81: us-gaap:NetCashProvidedByUsedInOperatingActivities | C81: NetCashProvidedByUsedInOperatingActivities | D81: USD | E81: 90000000 | F81: 2021-01-01 | G81: 2021-12-31 | H81: 0000000001-21-000001 | I81: 2022-02-01 | J81: 10-K | K81: companyfacts | M81: https://www.sec.gov/Archives/edgar/data/1/000000000121000001/annual.htm | N81: 'Cash Flow'!B5; 'Cash Flow Detail'!B5; 'Data Sheet'!B38 | U81: -3
A82: Cash Flow | B82: us-gaap:NetCashProvidedByUsedInOperatingActivities | C82: NetCashProvidedByUsedInOperatingActivities | D82: USD | E82: 100000000 | F82: 2022-01-01 | G82: 2022-12-31 | H82: 0000000001-22-000001 | I82: 2023-02-01 | J82: 10-K | K82: companyfacts | M82: https://www.sec.gov/Archives/edgar/data/1/000000000122000001/annual.htm | N82: 'Cash Flow'!C5; 'Cash Flow Detail'!C5; 'Data Sheet'!C38 | U82: -3
A83: Cash Flow | B83: us-gaap:NetCashProvidedByUsedInOperatingActivities | C83: NetCashProvidedByUsedInOperatingActivities | D83: USD | E83: 110000000 | F83: 2023-01-01 | G83: 2023-12-31 | H83: 0000000001-23-000001 | I83: 2024-02-01 | J83: 10-K | K83: companyfacts | M83: https://www.sec.gov/Archives/edgar/data/1/000000000123000001/annual.htm | N83: 'Cash Flow'!D5; 'Cash Flow Detail'!D5; 'Data Sheet'!D38 | U83: -3
A84: Cash Flow | B84: us-gaap:NetCashProvidedByUsedInOperatingActivities | C84: NetCashProvidedByUsedInOperatingActivities | D84: USD | E84: 150000000 | F84: 2024-01-01 | G84: 2024-12-31 | H84: 0000000001-24-000001 | I84: 2025-02-01 | J84: 10-K | K84: companyfacts | M84: https://www.sec.gov/Archives/edgar/data/1/000000000124000001/annual.htm | N84: 'Cash Flow'!E5; 'Cash Flow Detail'!E5; 'Data Sheet'!E38 | U84: -3
A85: Cash Flow | B85: us-gaap:PaymentsToAcquirePropertyPlantAndEquipment | C85: PaymentsToAcquirePropertyPlantAndEquipment | D85: USD | E85: 30000000 | F85: 2021-01-01 | G85: 2021-12-31 | H85: 0000000001-21-000001 | I85: 2022-02-01 | J85: 10-K | K85: companyfacts | M85: https://www.sec.gov/Archives/edgar/data/1/000000000121000001/annual.htm | N85: 'Cash Flow Detail'!B6; 'Data Sheet'!B39 | U85: -3
A86: Cash Flow | B86: us-gaap:PaymentsToAcquirePropertyPlantAndEquipment | C86: PaymentsToAcquirePropertyPlantAndEquipment | D86: USD | E86: 40000000 | F86: 2022-01-01 | G86: 2022-12-31 | H86: 0000000001-22-000001 | I86: 2023-02-01 | J86: 10-K | K86: companyfacts | M86: https://www.sec.gov/Archives/edgar/data/1/000000000122000001/annual.htm | N86: 'Cash Flow Detail'!C6; 'Data Sheet'!C39 | U86: -3
A87: Cash Flow | B87: us-gaap:PaymentsToAcquirePropertyPlantAndEquipment | C87: PaymentsToAcquirePropertyPlantAndEquipment | D87: USD | E87: 45000000 | F87: 2023-01-01 | G87: 2023-12-31 | H87: 0000000001-23-000001 | I87: 2024-02-01 | J87: 10-K | K87: companyfacts | M87: https://www.sec.gov/Archives/edgar/data/1/000000000123000001/annual.htm | N87: 'Cash Flow Detail'!D6; 'Data Sheet'!D39 | U87: -3
A88: Cash Flow | B88: us-gaap:PaymentsToAcquirePropertyPlantAndEquipment | C88: PaymentsToAcquirePropertyPlantAndEquipment | D88: USD | E88: 50000000 | F88: 2024-01-01 | G88: 2024-12-31 | H88: 0000000001-24-000001 | I88: 2025-02-01 | J88: 10-K | K88: companyfacts | M88: https://www.sec.gov/Archives/edgar/data/1/000000000124000001/annual.htm | N88: 'Cash Flow Detail'!E6; 'Data Sheet'!E39 | U88: -3
A89: Profit & Loss | B89: us-gaap:IncomeLossFromContinuingOperationsBeforeIncomeTaxesExtraordinaryItemsNoncontrollingInterest | C89: IncomeLossFromContinuingOperationsBeforeIncomeTaxesExtraordinaryItemsNoncontrollingInterest | D89: USD | E89: 75000000 | F89: 2021-01-01 | G89: 2021-12-31 | H89: 0000000001-21-000001 | I89: 2022-02-01 | J89: 10-K | K89: companyfacts | M89: https://www.sec.gov/Archives/edgar/data/1/000000000121000001/annual.htm | N89: 'Profit & Loss'!B13; 'Data Sheet'!B14 | U89: -3
A90: Profit & Loss | B90: us-gaap:IncomeLossFromContinuingOperationsBeforeIncomeTaxesExtraordinaryItemsNoncontrollingInterest | C90: IncomeLossFromContinuingOperationsBeforeIncomeTaxesExtraordinaryItemsNoncontrollingInterest | D90: USD | E90: 87500000 | F90: 2022-01-01 | G90: 2022-12-31 | H90: 0000000001-22-000001 | I90: 2023-02-01 | J90: 10-K | K90: companyfacts | M90: https://www.sec.gov/Archives/edgar/data/1/000000000122000001/annual.htm | N90: 'Profit & Loss'!C13; 'Data Sheet'!C14 | U90: -3
A91: Profit & Loss | B91: us-gaap:IncomeLossFromContinuingOperationsBeforeIncomeTaxesExtraordinaryItemsNoncontrollingInterest | C91: IncomeLossFromContinuingOperationsBeforeIncomeTaxesExtraordinaryItemsNoncontrollingInterest | D91: USD | E91: 100000000 | F91: 2023-01-01 | G91: 2023-12-31 | H91: 0000000001-23-000001 | I91: 2024-02-01 | J91: 10-K | K91: companyfacts | M91: https://www.sec.gov/Archives/edgar/data/1/000000000123000001/annual.htm | N91: 'Profit & Loss'!D13; 'Data Sheet'!D14 | U91: -3
A92: Profit & Loss | B92: us-gaap:IncomeLossFromContinuingOperationsBeforeIncomeTaxesExtraordinaryItemsNoncontrollingInterest | C92: IncomeLossFromContinuingOperationsBeforeIncomeTaxesExtraordinaryItemsNoncontrollingInterest | D92: USD | E92: 150000000 | F92: 2024-01-01 | G92: 2024-12-31 | H92: 0000000001-24-000001 | I92: 2025-02-01 | J92: 10-K | K92: companyfacts | M92: https://www.sec.gov/Archives/edgar/data/1/000000000124000001/annual.htm | N92: 'Profit & Loss'!E13; 'Data Sheet'!E14 | U92: -3
... A96: Profit & Loss | B96: us-gaap:IncomeTaxExpenseBenefit | C96: IncomeTaxExpenseBenefit | D96: USD | E96: 30000000 | F96: 2024-01-01 | G96: 2024-12-31 | H96: 0000000001-24-000001 | I96: 2025-02-01 | J96: 10-K | K96: companyfacts | M96: https://www.sec.gov/Archives/edgar/data/1/000000000124000001/annual.htm | N96: 'Profit & Loss'!E14; 'Data Sheet'!E15 | U96: -3
A97: Balance Sheet | B97: us-gaap:StockholdersEquityIncludingPortionAttributableToNoncontrollingInterest | C97: StockholdersEquityIncludingPortionAttributableToNoncontrollingInterest | D97: USD | E97: 410000000 | G97: 2021-12-31 | H97: 0000000001-21-000001 | I97: 2022-02-01 | J97: 10-K | K97: companyfacts | M97: https://www.sec.gov/Archives/edgar/data/1/000000000121000001/annual.htm | N97: 'Balance Sheet'!B16; 'Data Sheet'!B34 | U97: -3
A98: Balance Sheet | B98: us-gaap:StockholdersEquityIncludingPortionAttributableToNoncontrollingInterest | C98: StockholdersEquityIncludingPortionAttributableToNoncontrollingInterest | D98: USD | E98: 460000000 | G98: 2022-12-31 | H98: 0000000001-22-000001 | I98: 2023-02-01 | J98: 10-K | K98: companyfacts | M98: https://www.sec.gov/Archives/edgar/data/1/000000000122000001/annual.htm | N98: 'Balance Sheet'!C16; 'Data Sheet'!C34 | U98: -3
A99: Balance Sheet | B99: us-gaap:StockholdersEquityIncludingPortionAttributableToNoncontrollingInterest | C99: StockholdersEquityIncludingPortionAttributableToNoncontrollingInterest | D99: USD | E99: 510000000 | G99: 2023-12-31 | H99: 0000000001-23-000001 | I99: 2024-02-01 | J99: 10-K | K99: companyfacts | M99: https://www.sec.gov/Archives/edgar/data/1/000000000123000001/annual.htm | N99: 'Balance Sheet'!D16; 'Data Sheet'!D34 | U99: -3
A100: Balance Sheet | B100: us-gaap:StockholdersEquityIncludingPortionAttributableToNoncontrollingInterest | C100: StockholdersEquityIncludingPortionAttributableToNoncontrollingInterest | D100: USD | E100: 620000000 | G100: 2024-12-31 | H100: 0000000001-24-000001 | I100: 2025-02-01 | J100: 10-K | K100: companyfacts | M100: https://www.sec.gov/Archives/edgar/data/1/000000000124000001/annual.htm | N100: 'Balance Sheet'!E16; 'Data Sheet'!E34 | U100: -3
A101: Cash Flow | B101: us-gaap:DepreciationDepletionAndAmortization | C101: DepreciationDepletionAndAmortization | D101: USD | E101: 20000000 | F101: 2021-01-01 | G101: 2021-12-31 | H101: 0000000001-21-000001 | I101: 2022-02-01 | J101: 10-K | K101: companyfacts | M101: https://www.sec.gov/Archives/edgar/data/1/000000000121000001/annual.htm | N101: 'Cash Flow Detail'!B7; 'Data Sheet'!B40 | U101: -3
A102: Cash Flow | B102: us-gaap:DepreciationDepletionAndAmortization | C102: DepreciationDepletionAndAmortization | D102: USD | E102: 22000000 | F102: 2022-01-01 | G102: 2022-12-31 | H102: 0000000001-22-000001 | I102: 2023-02-01 | J102: 10-K | K102: companyfacts | M102: https://www.sec.gov/Archives/edgar/data/1/000000000122000001/annual.htm | N102: 'Cash Flow Detail'!C7; 'Data Sheet'!C40 | U102: -3
A103: Cash Flow | B103: us-gaap:DepreciationDepletionAndAmortization | C103: DepreciationDepletionAndAmortization | D103: USD | E103: 25000000 | F103: 2023-01-01 | G103: 2023-12-31 | H103: 0000000001-23-000001 | I103: 2024-02-01 | J103: 10-K | K103: companyfacts | M103: https://www.sec.gov/Archives/edgar/data/1/000000000123000001/annual.htm | N103: 'Cash Flow Detail'!D7; 'Data Sheet'!D40 | U103: -3
A104: Cash Flow | B104: us-gaap:DepreciationDepletionAndAmortization | C104: DepreciationDepletionAndAmortization | D104: USD | E104: 30000000 | F104: 2024-01-01 | G104: 2024-12-31 | H104: 0000000001-24-000001 | I104: 2025-02-01 | J104: 10-K | K104: companyfacts | M104: https://www.sec.gov/Archives/edgar/data/1/000000000124000001/annual.htm | N104: 'Cash Flow Detail'!E7; 'Data Sheet'!E40 | U104: -3
A105: Cash Flow | B105: us-gaap:PaymentsOfDividendsCommonStock | C105: PaymentsOfDividendsCommonStock | D105: USD | E105: 10000000 | F105: 2021-01-01 | G105: 2021-12-31 | H105: 0000000001-21-000001 | I105: 2022-02-01 | J105: 10-K | K105: companyfacts | M105: https://www.sec.gov/Archives/edgar/data/1/000000000121000001/annual.htm | N105: 'Cash Flow Detail'!B8; 'Data Sheet'!B41 | U105: -3
A106: Cash Flow | B106: us-gaap:PaymentsOfDividendsCommonStock | C106: PaymentsOfDividendsCommonStock | D106: USD | E106: 12000000 | F106: 2022-01-01 | G106: 2022-12-31 | H106: 0000000001-22-000001 | I106: 2023-02-01 | J106: 10-K | K106: companyfacts | M106: https://www.sec.gov/Archives/edgar/data/1/000000000122000001/annual.htm | N106: 'Cash Flow Detail'!C8; 'Data Sheet'!C41 | U106: -3
A107: Cash Flow | B107: us-gaap:PaymentsOfDividendsCommonStock | C107: PaymentsOfDividendsCommonStock | D107: USD | E107: 15000000 | F107: 2023-01-01 | G107: 2023-12-31 | H107: 0000000001-23-000001 | I107: 2024-02-01 | J107: 10-K | K107: companyfacts | M107: https://www.sec.gov/Archives/edgar/data/1/000000000123000001/annual.htm | N107: 'Cash Flow Detail'!D8; 'Data Sheet'!D41 | U107: -3
A108: Cash Flow | B108: us-gaap:PaymentsOfDividendsCommonStock | C108: PaymentsOfDividendsCommonStock | D108: USD | E108: 20000000 | F108: 2024-01-01 | G108: 2024-12-31 | H108: 0000000001-24-000001 | I108: 2025-02-01 | J108: 10-K | K108: companyfacts | M108: https://www.sec.gov/Archives/edgar/data/1/000000000124000001/annual.htm | N108: 'Cash Flow Detail'!E8; 'Data Sheet'!E41 | U108: -3
A109: Cash Flow | B109: us-gaap:PaymentsForRepurchaseOfCommonStock | C109: PaymentsForRepurchaseOfCommonStock | D109: USD | E109: 20000000 | F109: 2021-01-01 | G109: 2021-12-31 | H109: 0000000001-21-000001 | I109: 2022-02-01 | J109: 10-K | K109: companyfacts | M109: https://www.sec.gov/Archives/edgar/data/1/000000000121000001/annual.htm | N109: 'Cash Flow Detail'!B9; 'Data Sheet'!B42 | U109: -3
A110: Cash Flow | B110: us-gaap:PaymentsForRepurchaseOfCommonStock | C110: PaymentsForRepurchaseOfCommonStock | D110: USD | E110: 25000000 | F110: 2022-01-01 | G110: 2022-12-31 | H110: 0000000001-22-000001 | I110: 2023-02-01 | J110: 10-K | K110: companyfacts | M110: https://www.sec.gov/Archives/edgar/data/1/000000000122000001/annual.htm | N110: 'Cash Flow Detail'!C9; 'Data Sheet'!C42 | U110: -3
A111: Cash Flow | B111: us-gaap:PaymentsForRepurchaseOfCommonStock | C111: PaymentsForRepurchaseOfCommonStock | D111: USD | E111: 30000000 | F111: 2023-01-01 | G111: 2023-12-31 | H111: 0000000001-23-000001 | I111: 2024-02-01 | J111: 10-K | K111: companyfacts | M111: https://www.sec.gov/Archives/edgar/data/1/000000000123000001/annual.htm | N111: 'Cash Flow Detail'!D9; 'Data Sheet'!D42 | U111: -3
A112: Cash Flow | B112: us-gaap:PaymentsForRepurchaseOfCommonStock | C112: PaymentsForRepurchaseOfCommonStock | D112: USD | E112: 40000000 | F112: 2024-01-01 | G112: 2024-12-31 | H112: 0000000001-24-000001 | I112: 2025-02-01 | J112: 10-K | K112: companyfacts | M112: https://www.sec.gov/Archives/edgar/data/1/000000000124000001/annual.htm | N112: 'Cash Flow Detail'!E9; 'Data Sheet'!E42 | U112: -3
... A128: Profit & Loss | B128: us-gaap:WeightedAverageNumberOfDilutedSharesOutstanding | C128: WeightedAverageNumberOfDilutedSharesOutstanding | D128: shares | E128: 80000000 | F128: 2024-01-01 | G128: 2024-12-31 | H128: 0000000001-24-000001 | I128: 2025-02-01 | J128: 10-K | K128: companyfacts | M128: https://www.sec.gov/Archives/edgar/data/1/000000000124000001/annual.htm | N128: 'Profit & Loss'!E18; 'Data Sheet'!E19 | U128: -3
A129: Profit & Loss | B129: us-gaap:Revenues | C129: Revenues | D129: USD | E129: 1000000000 | F129: 2023-01-01 | G129: 2023-12-31 | H129: 0000000001-24-000001 | I129: 2025-02-01 | J129: 10-K | K129: companyfacts | M129: https://www.sec.gov/Archives/edgar/data/1/000000000124000001/annual.htm | U129: -3
A130: Profit & Loss | B130: us-gaap:CostOfRevenue | C130: CostOfRevenue | D130: USD | E130: 600000000 | F130: 2023-01-01 | G130: 2023-12-31 | H130: 0000000001-24-000001 | I130: 2025-02-01 | J130: 10-K | K130: companyfacts | M130: https://www.sec.gov/Archives/edgar/data/1/000000000124000001/annual.htm | U130: -3
A131: Profit & Loss | B131: us-gaap:GrossProfit | C131: GrossProfit | D131: USD | E131: 400000000 | F131: 2023-01-01 | G131: 2023-12-31 | H131: 0000000001-24-000001 | I131: 2025-02-01 | J131: 10-K | K131: companyfacts | M131: https://www.sec.gov/Archives/edgar/data/1/000000000124000001/annual.htm | U131: -3
A132: Profit & Loss | B132: us-gaap:OperatingIncomeLoss | C132: OperatingIncomeLoss | D132: USD | E132: 100000000 | F132: 2023-01-01 | G132: 2023-12-31 | H132: 0000000001-24-000001 | I132: 2025-02-01 | J132: 10-K | K132: companyfacts | M132: https://www.sec.gov/Archives/edgar/data/1/000000000124000001/annual.htm | U132: -3
A133: Profit & Loss | B133: us-gaap:ProfitLoss | C133: ProfitLoss | D133: USD | E133: 80000000 | F133: 2023-01-01 | G133: 2023-12-31 | H133: 0000000001-24-000001 | I133: 2025-02-01 | J133: 10-K | K133: companyfacts | M133: https://www.sec.gov/Archives/edgar/data/1/000000000124000001/annual.htm | U133: -3
A134: Profit & Loss | B134: us-gaap:NetIncomeLoss | C134: NetIncomeLoss | D134: USD | E134: 78000000 | F134: 2023-01-01 | G134: 2023-12-31 | H134: 0000000001-24-000001 | I134: 2025-02-01 | J134: 10-K | K134: companyfacts | M134: https://www.sec.gov/Archives/edgar/data/1/000000000124000001/annual.htm | U134: -3
A135: Profit & Loss | B135: us-gaap:NetIncomeLossAvailableToCommonStockholdersBasic | C135: NetIncomeLossAvailableToCommonStockholdersBasic | D135: USD | E135: 78000000 | F135: 2023-01-01 | G135: 2023-12-31 | H135: 0000000001-24-000001 | I135: 2025-02-01 | J135: 10-K | K135: companyfacts | M135: https://www.sec.gov/Archives/edgar/data/1/000000000124000001/annual.htm | U135: -3
A136: Profit & Loss | B136: us-gaap:InterestExpense | C136: InterestExpense | D136: USD | E136: 10000000 | F136: 2023-01-01 | G136: 2023-12-31 | H136: 0000000001-24-000001 | I136: 2025-02-01 | J136: 10-K | K136: companyfacts | M136: https://www.sec.gov/Archives/edgar/data/1/000000000124000001/annual.htm | U136: -3
A137: Balance Sheet | B137: us-gaap:Assets | C137: Assets | D137: USD | E137: 1100000000 | G137: 2023-12-31 | H137: 0000000001-24-000001 | I137: 2025-02-01 | J137: 10-K | K137: companyfacts | M137: https://www.sec.gov/Archives/edgar/data/1/000000000124000001/annual.htm | U137: -3
A138: Balance Sheet | B138: us-gaap:LiabilitiesAndStockholdersEquity | C138: LiabilitiesAndStockholdersEquity | D138: USD | E138: 1100000000 | G138: 2023-12-31 | H138: 0000000001-24-000001 | I138: 2025-02-01 | J138: 10-K | K138: companyfacts | M138: https://www.sec.gov/Archives/edgar/data/1/000000000124000001/annual.htm | U138: -3
A139: Balance Sheet | B139: us-gaap:AssetsCurrent | C139: AssetsCurrent | D139: USD | E139: 350000000 | G139: 2023-12-31 | H139: 0000000001-24-000001 | I139: 2025-02-01 | J139: 10-K | K139: companyfacts | M139: https://www.sec.gov/Archives/edgar/data/1/000000000124000001/annual.htm | U139: -3
A140: Balance Sheet | B140: us-gaap:LiabilitiesCurrent | C140: LiabilitiesCurrent | D140: USD | E140: 140000000 | G140: 2023-12-31 | H140: 0000000001-24-000001 | I140: 2025-02-01 | J140: 10-K | K140: companyfacts | M140: https://www.sec.gov/Archives/edgar/data/1/000000000124000001/annual.htm | U140: -3
A141: Balance Sheet | B141: us-gaap:CashAndCashEquivalentsAtCarryingValue | C141: CashAndCashEquivalentsAtCarryingValue | D141: USD | E141: 50000000 | G141: 2023-12-31 | H141: 0000000001-24-000001 | I141: 2025-02-01 | J141: 10-K | K141: companyfacts | M141: https://www.sec.gov/Archives/edgar/data/1/000000000124000001/annual.htm | U141: -3
A142: Balance Sheet | B142: us-gaap:ShortTermInvestments | C142: ShortTermInvestments | D142: USD | E142: 15000000 | G142: 2023-12-31 | H142: 0000000001-24-000001 | I142: 2025-02-01 | J142: 10-K | K142: companyfacts | M142: https://www.sec.gov/Archives/edgar/data/1/000000000124000001/annual.htm | U142: -3
A143: Balance Sheet | B143: us-gaap:AccountsReceivableNetCurrent | C143: AccountsReceivableNetCurrent | D143: USD | E143: 90000000 | G143: 2023-12-31 | H143: 0000000001-24-000001 | I143: 2025-02-01 | J143: 10-K | K143: companyfacts | M143: https://www.sec.gov/Archives/edgar/data/1/000000000124000001/annual.htm | U143: -3
A144: Balance Sheet | B144: us-gaap:InventoryNet | C144: InventoryNet | D144: USD | E144: 120000000 | G144: 2023-12-31 | H144: 0000000001-24-000001 | I144: 2025-02-01 | J144: 10-K | K144: companyfacts | M144: https://www.sec.gov/Archives/edgar/data/1/000000000124000001/annual.htm | U144: -3
A145: Balance Sheet | B145: us-gaap:AccountsPayableCurrent | C145: AccountsPayableCurrent | D145: USD | E145: 70000000 | G145: 2023-12-31 | H145: 0000000001-24-000001 | I145: 2025-02-01 | J145: 10-K | K145: companyfacts | M145: https://www.sec.gov/Archives/edgar/data/1/000000000124000001/annual.htm | U145: -3
A146: Balance Sheet | B146: us-gaap:CommonStockholdersEquity | C146: CommonStockholdersEquity | D146: USD | E146: 500000000 | G146: 2023-12-31 | H146: 0000000001-24-000001 | I146: 2025-02-01 | J146: 10-K | K146: companyfacts | M146: https://www.sec.gov/Archives/edgar/data/1/000000000124000001/annual.htm | U146: -3
A147: Balance Sheet | B147: us-gaap:DebtAndCapitalLeaseObligations | C147: DebtAndCapitalLeaseObligations | D147: USD | E147: 150000000 | G147: 2023-12-31 | H147: 0000000001-24-000001 | I147: 2025-02-01 | J147: 10-K | K147: companyfacts | M147: https://www.sec.gov/Archives/edgar/data/1/000000000124000001/annual.htm | U147: -3
A148: Cash Flow | B148: us-gaap:NetCashProvidedByUsedInOperatingActivities | C148: NetCashProvidedByUsedInOperatingActivities | D148: USD | E148: 110000000 | F148: 2023-01-01 | G148: 2023-12-31 | H148: 0000000001-24-000001 | I148: 2025-02-01 | J148: 10-K | K148: companyfacts | M148: https://www.sec.gov/Archives/edgar/data/1/000000000124000001/annual.htm | U148: -3
A149: Cash Flow | B149: us-gaap:PaymentsToAcquirePropertyPlantAndEquipment | C149: PaymentsToAcquirePropertyPlantAndEquipment | D149: USD | E149: 45000000 | F149: 2023-01-01 | G149: 2023-12-31 | H149: 0000000001-24-000001 | I149: 2025-02-01 | J149: 10-K | K149: companyfacts | M149: https://www.sec.gov/Archives/edgar/data/1/000000000124000001/annual.htm | U149: -3
A150: Profit & Loss | B150: us-gaap:IncomeLossFromContinuingOperationsBeforeIncomeTaxesExtraordinaryItemsNoncontrollingInterest | C150: IncomeLossFromContinuingOperationsBeforeIncomeTaxesExtraordinaryItemsNoncontrollingInterest | D150: USD | E150: 100000000 | F150: 2023-01-01 | G150: 2023-12-31 | H150: 0000000001-24-000001 | I150: 2025-02-01 | J150: 10-K | K150: companyfacts | M150: https://www.sec.gov/Archives/edgar/data/1/000000000124000001/annual.htm | U150: -3
A151: Profit & Loss | B151: us-gaap:IncomeTaxExpenseBenefit | C151: IncomeTaxExpenseBenefit | D151: USD | E151: 20000000 | F151: 2023-01-01 | G151: 2023-12-31 | H151: 0000000001-24-000001 | I151: 2025-02-01 | J151: 10-K | K151: companyfacts | M151: https://www.sec.gov/Archives/edgar/data/1/000000000124000001/annual.htm | U151: -3
A152: Balance Sheet | B152: us-gaap:StockholdersEquityIncludingPortionAttributableToNoncontrollingInterest | C152: StockholdersEquityIncludingPortionAttributableToNoncontrollingInterest | D152: USD | E152: 510000000 | G152: 2023-12-31 | H152: 0000000001-24-000001 | I152: 2025-02-01 | J152: 10-K | K152: companyfacts | M152: https://www.sec.gov/Archives/edgar/data/1/000000000124000001/annual.htm | U152: -3
A153: Cash Flow | B153: us-gaap:DepreciationDepletionAndAmortization | C153: DepreciationDepletionAndAmortization | D153: USD | E153: 25000000 | F153: 2023-01-01 | G153: 2023-12-31 | H153: 0000000001-24-000001 | I153: 2025-02-01 | J153: 10-K | K153: companyfacts | M153: https://www.sec.gov/Archives/edgar/data/1/000000000124000001/annual.htm | U153: -3
A154: Cash Flow | B154: us-gaap:PaymentsOfDividendsCommonStock | C154: PaymentsOfDividendsCommonStock | D154: USD | E154: 15000000 | F154: 2023-01-01 | G154: 2023-12-31 | H154: 0000000001-24-000001 | I154: 2025-02-01 | J154: 10-K | K154: companyfacts | M154: https://www.sec.gov/Archives/edgar/data/1/000000000124000001/annual.htm | U154: -3
A155: Cash Flow | B155: us-gaap:PaymentsForRepurchaseOfCommonStock | C155: PaymentsForRepurchaseOfCommonStock | D155: USD | E155: 30000000 | F155: 2023-01-01 | G155: 2023-12-31 | H155: 0000000001-24-000001 | I155: 2025-02-01 | J155: 10-K | K155: companyfacts | M155: https://www.sec.gov/Archives/edgar/data/1/000000000124000001/annual.htm | U155: -3
A156: Profit & Loss | B156: us-gaap:CommonStockDividendsPerShareDeclared | C156: CommonStockDividendsPerShareDeclared | D156: USD/shares | E156: 0.15 | F156: 2023-01-01 | G156: 2023-12-31 | H156: 0000000001-24-000001 | I156: 2025-02-01 | J156: 10-K | K156: companyfacts | M156: https://www.sec.gov/Archives/edgar/data/1/000000000124000001/annual.htm | U156: 3
A157: Profit & Loss | B157: us-gaap:EarningsPerShareBasic | C157: EarningsPerShareBasic | D157: USD/shares | E157: 0.78 | F157: 2023-01-01 | G157: 2023-12-31 | H157: 0000000001-24-000001 | I157: 2025-02-01 | J157: 10-K | K157: companyfacts | M157: https://www.sec.gov/Archives/edgar/data/1/000000000124000001/annual.htm | U157: 3
A158: Profit & Loss | B158: us-gaap:EarningsPerShareDiluted | C158: EarningsPerShareDiluted | D158: USD/shares | E158: 0.78 | F158: 2023-01-01 | G158: 2023-12-31 | H158: 0000000001-24-000001 | I158: 2025-02-01 | J158: 10-K | K158: companyfacts | M158: https://www.sec.gov/Archives/edgar/data/1/000000000124000001/annual.htm | U158: 3
A159: Profit & Loss | B159: us-gaap:WeightedAverageNumberOfDilutedSharesOutstanding | C159: WeightedAverageNumberOfDilutedSharesOutstanding | D159: shares | E159: 100000000 | F159: 2023-01-01 | G159: 2023-12-31 | H159: 0000000001-24-000001 | I159: 2025-02-01 | J159: 10-K | K159: companyfacts | M159: https://www.sec.gov/Archives/edgar/data/1/000000000124000001/annual.htm | U159: -3
A160: Disclosure | B160: us-gaap:Revenues | C160: Retail revenue | D160: USD | E160: 400000000 | F160: 2023-01-01 | G160: 2023-12-31 | H160: 0000000001-24-000001 | I160: 2025-02-01 | J160: 10-K | K160: companyfacts | M160: https://www.sec.gov/Archives/edgar/data/1/000000000124000001/annual.htm | R160: Revenue & Segments | S160: retail2023 | T160: demo:BusinessSegmentsAxis=demo:RetailMember | U160: -3
A161: Disclosure | B161: us-gaap:Revenues | C161: Retail revenue | D161: USD | E161: 600000000 | F161: 2024-01-01 | G161: 2024-12-31 | H161: 0000000001-24-000001 | I161: 2025-02-01 | J161: 10-K | K161: companyfacts | M161: https://www.sec.gov/Archives/edgar/data/1/000000000124000001/annual.htm | R161: Revenue & Segments | S161: retail2024 | T161: demo:BusinessSegmentsAxis=demo:RetailMember | U161: -3
A162: Disclosure | B162: demo:ActiveAccounts | C162: Active accounts | D162: pure | E162: 10 | G162: 2023-12-31 | H162: 0000000001-24-000001 | I162: 2025-02-01 | J162: 10-K | K162: companyfacts | L162: Reviewed KPI: active accounts at fiscal end, not unique people. | M162: https://www.sec.gov/Archives/edgar/data/1/000000000124000001/annual.htm | Q162: kpi:demo:ActiveAccounts | R162: Operating KPIs | U162: 0
A163: Disclosure | B163: demo:ActiveAccounts | C163: Active accounts | D163: pure | E163: 12 | G163: 2024-12-31 | H163: 0000000001-24-000001 | I163: 2025-02-01 | J163: 10-K | K163: companyfacts | L163: Reviewed KPI: active accounts at fiscal end, not unique people. | M163: https://www.sec.gov/Archives/edgar/data/1/000000000124000001/annual.htm | Q163: kpi:demo:ActiveAccounts | R163: Operating KPIs | U163: 0

Sheet Sources & Coverage
A1: Historical teaching fixture | Sources & Coverage
A2: 4 selected annual period ends (20 maximum) | 159 raw facts | 0 discovered filings | 0 extraction coverage records
A4: Record | B4: Accession | C4: Form | D4: Report end | E4: Filed | F4: Status | G4: Detail | H4: Source filing
A5: Presentation policy | F5: Latest 20 fiscal periods | G5: Statement tabs and Data Sheet use the same selected financial facts and a maximum of 20 fiscal periods. Source Data retains all supplied raw observations, including older and unselected facts; those are not additional presented periods.

Sheet Read Me
A1: Historical teaching fixture | Read Me
A2: Fishtorian · Historical financial research. Reported facts, transparent calculations, traceable sources.
A4: Topic | B4: Explanation
A5: Company | B5: Historical teaching fixture
A6: Ticker | B6: HIST
A7: SEC CIK | B7: 0000000001
A8: Generated (UTC) | B8: 2026-10-08T03:43:33.903333+00:00
A9: Annual history | B9: Presentation is limited to the latest 20 selected fiscal periods, in chronological order. Statement tabs and Data Sheet retain the same selected columns, including entirely unavailable periods and internal gaps as blanks, matching the online presentation. Sources & Coverage lists unavailable statement periods. Raw observations outside the presentation window may remain in Source Data. Available data does not prove complete lifetime coverage.
A10: Presentation | B10: The main statements use annual columns, section headings and bold reported totals. Cash Flow presents reported cash reconciliation totals; Cash Flow Detail retains every selected company cash-flow line. Data Sheet combines Profit & Loss, Balance Sheet and full Cash Flow in a clean annual matrix using the same selected facts, units and signs. No forecasts, valuations or synthetic totals are added.
A11: Units | B11: Pure currency amounts display in millions of their own reported currency. Shares, currency per share, ratios and all other units are unscaled. The statement note specifies a single reported currency; mixed currencies and other units are identified in row labels. Each cell comment records its exact reported and display unit. No currency conversion occurs.
A12: Data Sheet columns | B12: Column A: reported line item, with units where needed. Columns B through at most U: selected annual fiscal period ends, oldest to newest, repeated for each statement block. Source tags, dates, accessions and links stay in value-cell comments and the separate Source Data audit table.
A13: Raw values | B13: Source Data stores every supplied raw fact and every selected statement fact, unscaled. Displayed cells identifies every statement or Data Sheet cell using each selected fact.
A14: Presentation signs | B14: Where the filing's visible statement sign is available, statement tabs and Data Sheet use that presentation value. For example, an XBRL payments concept can be positive while its cash-flow line is shown negative. Source Data keeps the underlying Source/XBRL value and optional Statement presentation value separately, both unscaled.
A15: Cash-flow reconciliation | B15: Beginning and ending cash can use the same original SEC concept with different instant dates. They remain separate reported rows, identified by cash_begin/cash_end row roles. Annual display period columns identify the verified year being reconciled; Original source instant preserves each actual XBRL context date. These display periods do not turn cash balances into duration facts.
... A30: Withheld inconsistent cells | B30: 0

Sheet Calculation Inputs
A1: Historical teaching fixture | Calculation Inputs
A2: Unscaled calculation graph · source facts and intermediate formulas
A4: ID | B4: Description | C4: Period | D4: Unit | E4: Value / formula | F4: Status | G4: Explanation | H4: Source tag | I4: Original label | J4: Accession | K4: Filed | L4: Source URL | M4: Context | N4: Dimensions | O4: Source decimals
A5: I1 | B5: Revenues | C5: 2021-12-31 | D5: USD | E5: 800000000 | F5: available | H5: us-gaap:Revenues | I5: Revenues | J5: 0000000001-21-000001 | K5: 2022-02-01 | L5: https://www.sec.gov/Archives/edgar/data/1/000000000121000001/annual.htm | O5: -3
A6: I2 | B6: Revenues | C6: 2022-12-31 | D6: USD | E6: 900000000 | F6: available | H6: us-gaap:Revenues | I6: Revenues | J6: 0000000001-22-000001 | K6: 2023-02-01 | L6: https://www.sec.gov/Archives/edgar/data/1/000000000122000001/annual.htm | O6: -3
A7: I3 | B7: Revenues | C7: 2023-12-31 | D7: USD | E7: 1000000000 | F7: available | H7: us-gaap:Revenues | I7: Revenues | J7: 0000000001-23-000001 | K7: 2024-02-01 | L7: https://www.sec.gov/Archives/edgar/data/1/000000000123000001/annual.htm | O7: -3
A8: I4 | B8: Revenues | C8: 2024-12-31 | D8: USD | E8: 1200000000 | F8: available | H8: us-gaap:Revenues | I8: Revenues | J8: 0000000001-24-000001 | K8: 2025-02-01 | L8: https://www.sec.gov/Archives/edgar/data/1/000000000124000001/annual.htm | O8: -3
A9: I5 | B9: GrossProfit | C9: 2021-12-31 | D9: USD | E9: 300000000 | F9: available | H9: us-gaap:GrossProfit | I9: GrossProfit | J9: 0000000001-21-000001 | K9: 2022-02-01 | L9: https://www.sec.gov/Archives/edgar/data/1/000000000121000001/annual.htm | O9: -3
A10: I6 | B10: GrossProfit | C10: 2022-12-31 | D10: USD | E10: 350000000 | F10: available | H10: us-gaap:GrossProfit | I10: GrossProfit | J10: 0000000001-22-000001 | K10: 2023-02-01 | L10: https://www.sec.gov/Archives/edgar/data/1/000000000122000001/annual.htm | O10: -3
A11: I7 | B11: GrossProfit | C11: 2023-12-31 | D11: USD | E11: 400000000 | F11: available | H11: us-gaap:GrossProfit | I11: GrossProfit | J11: 0000000001-23-000001 | K11: 2024-02-01 | L11: https://www.sec.gov/Archives/edgar/data/1/000000000123000001/annual.htm | O11: -3
A12: I8 | B12: GrossProfit | C12: 2024-12-31 | D12: USD | E12: 500000000 | F12: available | H12: us-gaap:GrossProfit | I12: GrossProfit | J12: 0000000001-24-000001 | K12: 2025-02-01 | L12: https://www.sec.gov/Archives/edgar/data/1/000000000124000001/annual.htm | O12: -3
A13: I9 | B13: OperatingIncomeLoss | C13: 2021-12-31 | D13: USD | E13: 80000000 | F13: available | H13: us-gaap:OperatingIncomeLoss | I13: OperatingIncomeLoss | J13: 0000000001-21-000001 | K13: 2022-02-01 | L13: https://www.sec.gov/Archives/edgar/data/1/000000000121000001/annual.htm | O13: -3
A14: I10 | B14: OperatingIncomeLoss | C14: 2022-12-31 | D14: USD | E14: 90000000 | F14: available | H14: us-gaap:OperatingIncomeLoss | I14: OperatingIncomeLoss | J14: 0000000001-22-000001 | K14: 2023-02-01 | L14: https://www.sec.gov/Archives/edgar/data/1/000000000122000001/annual.htm | O14: -3
A15: I11 | B15: OperatingIncomeLoss | C15: 2023-12-31 | D15: USD | E15: 100000000 | F15: available | H15: us-gaap:OperatingIncomeLoss | I15: OperatingIncomeLoss | J15: 0000000001-23-000001 | K15: 2024-02-01 | L15: https://www.sec.gov/Archives/edgar/data/1/000000000123000001/annual.htm | O15: -3
A16: I12 | B16: OperatingIncomeLoss | C16: 2024-12-31 | D16: USD | E16: 180000000 | F16: available | H16: us-gaap:OperatingIncomeLoss | I16: OperatingIncomeLoss | J16: 0000000001-24-000001 | K16: 2025-02-01 | L16: https://www.sec.gov/Archives/edgar/data/1/000000000124000001/annual.htm | O16: -3
A17: I13 | B17: Retail revenue · Business Segments: Retail | C17: 2021-12-31 | D17: USD | F17: unavailable | G17: No unambiguous annual disclosure.
A18: I14 | B18: Retail revenue · Business Segments: Retail | C18: 2022-12-31 | D18: USD | F18: unavailable | G18: No unambiguous annual disclosure.
A19: I15 | B19: Retail revenue | C19: 2023-12-31 | D19: USD | E19: 400000000 | F19: available | H19: us-gaap:Revenues | I19: Retail revenue | J19: 0000000001-24-000001 | K19: 2025-02-01 | L19: https://www.sec.gov/Archives/edgar/data/1/000000000124000001/annual.htm | M19: retail2023 | N19: demo:BusinessSegmentsAxis=demo:RetailMember | O19: -3
A20: I16 | B20: Retail revenue | C20: 2024-12-31 | D20: USD | E20: 600000000 | F20: available | H20: us-gaap:Revenues | I20: Retail revenue | J20: 0000000001-24-000001 | K20: 2025-02-01 | L20: https://www.sec.gov/Archives/edgar/data/1/000000000124000001/annual.htm | M20: retail2024 | N20: demo:BusinessSegmentsAxis=demo:RetailMember | O20: -3
A21: I17 | B21: AssetsCurrent | C21: 2021-12-31 | D21: USD | E21: 250000000 | F21: available | H21: us-gaap:AssetsCurrent | I21: AssetsCurrent | J21: 0000000001-21-000001 | K21: 2022-02-01 | L21: https://www.sec.gov/Archives/edgar/data/1/000000000121000001/annual.htm | O21: -3
A22: I18 | B22: AssetsCurrent | C22: 2022-12-31 | D22: USD | E22: 300000000 | F22: available | H22: us-gaap:AssetsCurrent | I22: AssetsCurrent | J22: 0000000001-22-000001 | K22: 2023-02-01 | L22: https://www.sec.gov/Archives/edgar/data/1/000000000122000001/annual.htm | O22: -3
A23: I19 | B23: AssetsCurrent | C23: 2023-12-31 | D23: USD | E23: 350000000 | F23: available | H23: us-gaap:AssetsCurrent | I23: AssetsCurrent | J23: 0000000001-23-000001 | K23: 2024-02-01 | L23: https://www.sec.gov/Archives/edgar/data/1/000000000123000001/annual.htm | O23: -3
A24: I20 | B24: AssetsCurrent | C24: 2024-12-31 | D24: USD | E24: 400000000 | F24: available | H24: us-gaap:AssetsCurrent | I24: AssetsCurrent | J24: 0000000001-24-000001 | K24: 2025-02-01 | L24: https://www.sec.gov/Archives/edgar/data/1/000000000124000001/annual.htm | O24: -3
A25: I21 | B25: LiabilitiesCurrent | C25: 2021-12-31 | D25: USD | E25: 100000000 | F25: available | H25: us-gaap:LiabilitiesCurrent | I25: LiabilitiesCurrent | J25: 0000000001-21-000001 | K25: 2022-02-01 | L25: https://www.sec.gov/Archives/edgar/data/1/000000000121000001/annual.htm | O25: -3
A26: I22 | B26: LiabilitiesCurrent | C26: 2022-12-31 | D26: USD | E26: 120000000 | F26: available | H26: us-gaap:LiabilitiesCurrent | I26: LiabilitiesCurrent | J26: 0000000001-22-000001 | K26: 2023-02-01 | L26: https://www.sec.gov/Archives/edgar/data/1/000000000122000001/annual.htm | O26: -3
A27: I23 | B27: LiabilitiesCurrent | C27: 2023-12-31 | D27: USD | E27: 140000000 | F27: available | H27: us-gaap:LiabilitiesCurrent | I27: LiabilitiesCurrent | J27: 0000000001-23-000001 | K27: 2024-02-01 | L27: https://www.sec.gov/Archives/edgar/data/1/000000000123000001/annual.htm | O27: -3
A28: I24 | B28: LiabilitiesCurrent | C28: 2024-12-31 | D28: USD | E28: 160000000 | F28: available | H28: us-gaap:LiabilitiesCurrent | I28: LiabilitiesCurrent | J28: 0000000001-24-000001 | K28: 2025-02-01 | L28: https://www.sec.gov/Archives/edgar/data/1/000000000124000001/annual.htm | O28: -3
A29: I25 | B29: AccountsReceivableNetCurrent | C29: 2021-12-31 | D29: USD | E29: 70000000 | F29: available | H29: us-gaap:AccountsReceivableNetCurrent | I29: AccountsReceivableNetCurrent | J29: 0000000001-21-000001 | K29: 2022-02-01 | L29: https://www.sec.gov/Archives/edgar/data/1/000000000121000001/annual.htm | O29: -3
A30: I26 | B30: AccountsReceivableNetCurrent | C30: 2022-12-31 | D30: USD | E30: 80000000 | F30: available | H30: us-gaap:AccountsReceivableNetCurrent | I30: AccountsReceivableNetCurrent | J30: 0000000001-22-000001 | K30: 2023-02-01 | L30: https://www.sec.gov/Archives/edgar/data/1/000000000122000001/annual.htm | O30: -3
A31: I27 | B31: AccountsReceivableNetCurrent | C31: 2023-12-31 | D31: USD | E31: 90000000 | F31: available | H31: us-gaap:AccountsReceivableNetCurrent | I31: AccountsReceivableNetCurrent | J31: 0000000001-23-000001 | K31: 2024-02-01 | L31: https://www.sec.gov/Archives/edgar/data/1/000000000123000001/annual.htm | O31: -3
A32: I28 | B32: AccountsReceivableNetCurrent | C32: 2024-12-31 | D32: USD | E32: 110000000 | F32: available | H32: us-gaap:AccountsReceivableNetCurrent | I32: AccountsReceivableNetCurrent | J32: 0000000001-24-000001 | K32: 2025-02-01 | L32: https://www.sec.gov/Archives/edgar/data/1/000000000124000001/annual.htm | O32: -3
... A157: I153 | B157: IncomeLossFromContinuingOperationsBeforeIncomeTaxesExtraordinaryItemsNoncontrollingInterest | C157: 2021-12-31 | D157: USD | E157: 75000000 | F157: available | H157: us-gaap:IncomeLossFromContinuingOperationsBeforeIncomeTaxesExtraordinaryItemsNoncontrollingInterest | I157: IncomeLossFromContinuingOperationsBeforeIncomeTaxesExtraordinaryItemsNoncontrollingInterest | J157: 0000000001-21-000001 | K157: 2022-02-01 | L157: https://www.sec.gov/Archives/edgar/data/1/000000000121000001/annual.htm | O157: -3
A158: I154 | B158: NI plus tax less pretax reconciliation | C158: 2021-12-31 | D158: USD | E158: =E153+E154-E157 -> 0 | F158: available
A159: I155 | B159: EBITDA — reconciled historical definition | C159: 2021-12-31 | D159: USD | E159: =E153+E154+E155+E156+0*E158 -> 105000000 | F159: available
A160: I156 | B160: ProfitLoss | C160: 2022-12-31 | D160: USD | E160: 70000000 | F160: available | H160: us-gaap:ProfitLoss | I160: ProfitLoss | J160: 0000000001-22-000001 | K160: 2023-02-01 | L160: https://www.sec.gov/Archives/edgar/data/1/000000000122000001/annual.htm | O160: -3
A161: I157 | B161: IncomeTaxExpenseBenefit | C161: 2022-12-31 | D161: USD | E161: 17500000 | F161: available | H161: us-gaap:IncomeTaxExpenseBenefit | I161: IncomeTaxExpenseBenefit | J161: 0000000001-22-000001 | K161: 2023-02-01 | L161: https://www.sec.gov/Archives/edgar/data/1/000000000122000001/annual.htm | O161: -3
A162: I158 | B162: InterestExpense | C162: 2022-12-31 | D162: USD | E162: 10000000 | F162: available | H162: us-gaap:InterestExpense | I162: InterestExpense | J162: 0000000001-22-000001 | K162: 2023-02-01 | L162: https://www.sec.gov/Archives/edgar/data/1/000000000122000001/annual.htm | O162: -3
A163: I159 | B163: DepreciationDepletionAndAmortization | C163: 2022-12-31 | D163: USD | E163: 22000000 | F163: available | H163: us-gaap:DepreciationDepletionAndAmortization | I163: DepreciationDepletionAndAmortization | J163: 0000000001-22-000001 | K163: 2023-02-01 | L163: https://www.sec.gov/Archives/edgar/data/1/000000000122000001/annual.htm | O163: -3
A164: I160 | B164: IncomeLossFromContinuingOperationsBeforeIncomeTaxesExtraordinaryItemsNoncontrollingInterest | C164: 2022-12-31 | D164: USD | E164: 87500000 | F164: available | H164: us-gaap:IncomeLossFromContinuingOperationsBeforeIncomeTaxesExtraordinaryItemsNoncontrollingInterest | I164: IncomeLossFromContinuingOperationsBeforeIncomeTaxesExtraordinaryItemsNoncontrollingInterest | J164: 0000000001-22-000001 | K164: 2023-02-01 | L164: https://www.sec.gov/Archives/edgar/data/1/000000000122000001/annual.htm | O164: -3
A165: I161 | B165: NI plus tax less pretax reconciliation | C165: 2022-12-31 | D165: USD | E165: =E160+E161-E164 -> 0 | F165: available
A166: I162 | B166: EBITDA — reconciled historical definition | C166: 2022-12-31 | D166: USD | E166: =E160+E161+E162+E163+0*E165 -> 119500000 | F166: available
A167: I163 | B167: ProfitLoss | C167: 2023-12-31 | D167: USD | E167: 80000000 | F167: available | H167: us-gaap:ProfitLoss | I167: ProfitLoss | J167: 0000000001-23-000001 | K167: 2024-02-01 | L167: https://www.sec.gov/Archives/edgar/data/1/000000000123000001/annual.htm | O167: -3
A168: I164 | B168: IncomeTaxExpenseBenefit | C168: 2023-12-31 | D168: USD | E168: 20000000 | F168: available | H168: us-gaap:IncomeTaxExpenseBenefit | I168: IncomeTaxExpenseBenefit | J168: 0000000001-23-000001 | K168: 2024-02-01 | L168: https://www.sec.gov/Archives/edgar/data/1/000000000123000001/annual.htm | O168: -3
A169: I165 | B169: InterestExpense | C169: 2023-12-31 | D169: USD | E169: 10000000 | F169: available | H169: us-gaap:InterestExpense | I169: InterestExpense | J169: 0000000001-23-000001 | K169: 2024-02-01 | L169: https://www.sec.gov/Archives/edgar/data/1/000000000123000001/annual.htm | O169: -3
A170: I166 | B170: DepreciationDepletionAndAmortization | C170: 2023-12-31 | D170: USD | E170: 25000000 | F170: available | H170: us-gaap:DepreciationDepletionAndAmortization | I170: DepreciationDepletionAndAmortization | J170: 0000000001-23-000001 | K170: 2024-02-01 | L170: https://www.sec.gov/Archives/edgar/data/1/000000000123000001/annual.htm | O170: -3
A171: I167 | B171: IncomeLossFromContinuingOperationsBeforeIncomeTaxesExtraordinaryItemsNoncontrollingInterest | C171: 2023-12-31 | D171: USD | E171: 100000000 | F171: available | H171: us-gaap:IncomeLossFromContinuingOperationsBeforeIncomeTaxesExtraordinaryItemsNoncontrollingInterest | I171: IncomeLossFromContinuingOperationsBeforeIncomeTaxesExtraordinaryItemsNoncontrollingInterest | J171: 0000000001-23-000001 | K171: 2024-02-01 | L171: https://www.sec.gov/Archives/edgar/data/1/000000000123000001/annual.htm | O171: -3
A172: I168 | B172: NI plus tax less pretax reconciliation | C172: 2023-12-31 | D172: USD | E172: =E167+E168-E171 -> 0 | F172: available
A173: I169 | B173: EBITDA — reconciled historical definition | C173: 2023-12-31 | D173: USD | E173: =E167+E168+E169+E170+0*E172 -> 135000000 | F173: available
A174: I170 | B174: ProfitLoss | C174: 2024-12-31 | D174: USD | E174: 120000000 | F174: available | H174: us-gaap:ProfitLoss | I174: ProfitLoss | J174: 0000000001-24-000001 | K174: 2025-02-01 | L174: https://www.sec.gov/Archives/edgar/data/1/000000000124000001/annual.htm | O174: -3
A175: I171 | B175: IncomeTaxExpenseBenefit | C175: 2024-12-31 | D175: USD | E175: 30000000 | F175: available | H175: us-gaap:IncomeTaxExpenseBenefit | I175: IncomeTaxExpenseBenefit | J175: 0000000001-24-000001 | K175: 2025-02-01 | L175: https://www.sec.gov/Archives/edgar/data/1/000000000124000001/annual.htm | O175: -3
A176: I172 | B176: InterestExpense | C176: 2024-12-31 | D176: USD | E176: 12000000 | F176: available | H176: us-gaap:InterestExpense | I176: InterestExpense | J176: 0000000001-24-000001 | K176: 2025-02-01 | L176: https://www.sec.gov/Archives/edgar/data/1/000000000124000001/annual.htm | O176: -3
A177: I173 | B177: DepreciationDepletionAndAmortization | C177: 2024-12-31 | D177: USD | E177: 30000000 | F177: available | H177: us-gaap:DepreciationDepletionAndAmortization | I177: DepreciationDepletionAndAmortization | J177: 0000000001-24-000001 | K177: 2025-02-01 | L177: https://www.sec.gov/Archives/edgar/data/1/000000000124000001/annual.htm | O177: -3
A178: I174 | B178: IncomeLossFromContinuingOperationsBeforeIncomeTaxesExtraordinaryItemsNoncontrollingInterest | C178: 2024-12-31 | D178: USD | E178: 150000000 | F178: available | H178: us-gaap:IncomeLossFromContinuingOperationsBeforeIncomeTaxesExtraordinaryItemsNoncontrollingInterest | I178: IncomeLossFromContinuingOperationsBeforeIncomeTaxesExtraordinaryItemsNoncontrollingInterest | J178: 0000000001-24-000001 | K178: 2025-02-01 | L178: https://www.sec.gov/Archives/edgar/data/1/000000000124000001/annual.htm | O178: -3
A179: I175 | B179: NI plus tax less pretax reconciliation | C179: 2024-12-31 | D179: USD | E179: =E174+E175-E178 -> 0 | F179: available
A180: I176 | B180: EBITDA — reconciled historical definition | C180: 2024-12-31 | D180: USD | E180: =E174+E175+E176+E177+0*E179 -> 192000000 | F180: available
A181: I177 | B181: Revenues | C181: 2021-12-31 | D181: USD | E181: 800000000 | F181: available | H181: us-gaap:Revenues | I181: Revenues | J181: 0000000001-21-000001 | K181: 2022-02-01 | L181: https://www.sec.gov/Archives/edgar/data/1/000000000121000001/annual.htm | O181: -3
A182: I178 | B182: EBITDA margin — reconciled definition | C182: 2021-12-31 | D182: % | E182: =E159/E181 -> 0.13125 | F182: available
A183: I179 | B183: Revenues | C183: 2022-12-31 | D183: USD | E183: 900000000 | F183: available | H183: us-gaap:Revenues | I183: Revenues | J183: 0000000001-22-000001 | K183: 2023-02-01 | L183: https://www.sec.gov/Archives/edgar/data/1/000000000122000001/annual.htm | O183: -3
A184: I180 | B184: EBITDA margin — reconciled definition | C184: 2022-12-31 | D184: % | E184: =E166/E183 -> 0.13277778 | F184: available
A185: I181 | B185: Revenues | C185: 2023-12-31 | D185: USD | E185: 1000000000 | F185: available | H185: us-gaap:Revenues | I185: Revenues | J185: 0000000001-23-000001 | K185: 2024-02-01 | L185: https://www.sec.gov/Archives/edgar/data/1/000000000123000001/annual.htm | O185: -3
A186: I182 | B186: EBITDA margin — reconciled definition | C186: 2023-12-31 | D186: % | E186: =E173/E185 -> 0.135 | F186: available
A187: I183 | B187: Revenues | C187: 2024-12-31 | D187: USD | E187: 1200000000 | F187: available | H187: us-gaap:Revenues | I187: Revenues | J187: 0000000001-24-000001 | K187: 2025-02-01 | L187: https://www.sec.gov/Archives/edgar/data/1/000000000124000001/annual.htm | O187: -3
A188: I184 | B188: EBITDA margin — reconciled definition | C188: 2024-12-31 | D188: % | E188: =E180/E187 -> 0.16 | F188: available
A189: I185 | B189: StockholdersEquityIncludingPortionAttributableToNoncontrollingInterest | C189: 2021-12-31 | D189: USD | E189: 410000000 | F189: available | H189: us-gaap:StockholdersEquityIncludingPortionAttributableToNoncontrollingInterest | I189: StockholdersEquityIncludingPortionAttributableToNoncontrollingInterest | J189: 0000000001-21-000001 | K189: 2022-02-01 | L189: https://www.sec.gov/Archives/edgar/data/1/000000000121000001/annual.htm | O189: -3
A190: I186 | B190: Assets | C190: 2021-12-31 | D190: USD | E190: 800000000 | F190: available | H190: us-gaap:Assets | I190: Assets | J190: 0000000001-21-000001 | K190: 2022-02-01 | L190: https://www.sec.gov/Archives/edgar/data/1/000000000121000001/annual.htm | O190: -3
A191: I187 | B191: Consolidated equity / assets | C191: 2021-12-31 | D191: % | E191: =E189/E190 -> 0.5125 | F191: available
A192: I188 | B192: StockholdersEquityIncludingPortionAttributableToNoncontrollingInterest | C192: 2022-12-31 | D192: USD | E192: 460000000 | F192: available | H192: us-gaap:StockholdersEquityIncludingPortionAttributableToNoncontrollingInterest | I192: StockholdersEquityIncludingPortionAttributableToNoncontrollingInterest | J192: 0000000001-22-000001 | K192: 2023-02-01 | L192: https://www.sec.gov/Archives/edgar/data/1/000000000122000001/annual.htm | O192: -3
A193: I189 | B193: Assets | C193: 2022-12-31 | D193: USD | E193: 900000000 | F193: available | H193: us-gaap:Assets | I193: Assets | J193: 0000000001-22-000001 | K193: 2023-02-01 | L193: https://www.sec.gov/Archives/edgar/data/1/000000000122000001/annual.htm | O193: -3
A194: I190 | B194: Consolidated equity / assets | C194: 2022-12-31 | D194: % | E194: =E192/E193 -> 0.51111111 | F194: available
A195: I191 | B195: StockholdersEquityIncludingPortionAttributableToNoncontrollingInterest | C195: 2023-12-31 | D195: USD | E195: 510000000 | F195: available | H195: us-gaap:StockholdersEquityIncludingPortionAttributableToNoncontrollingInterest | I195: StockholdersEquityIncludingPortionAttributableToNoncontrollingInterest | J195: 0000000001-23-000001 | K195: 2024-02-01 | L195: https://www.sec.gov/Archives/edgar/data/1/000000000123000001/annual.htm | O195: -3
A196: I192 | B196: Assets | C196: 2023-12-31 | D196: USD | E196: 1100000000 | F196: available | H196: us-gaap:Assets | I196: Assets | J196: 0000000001-23-000001 | K196: 2024-02-01 | L196: https://www.sec.gov/Archives/edgar/data/1/000000000123000001/annual.htm | O196: -3
A197: I193 | B197: Consolidated equity / assets | C197: 2023-12-31 | D197: % | E197: =E195/E196 -> 0.46363636 | F197: available
A198: I194 | B198: StockholdersEquityIncludingPortionAttributableToNoncontrollingInterest | C198: 2024-12-31 | D198: USD | E198: 620000000 | F198: available | H198: us-gaap:StockholdersEquityIncludingPortionAttributableToNoncontrollingInterest | I198: StockholdersEquityIncludingPortionAttributableToNoncontrollingInterest | J198: 0000000001-24-000001 | K198: 2025-02-01 | L198: https://www.sec.gov/Archives/edgar/data/1/000000000124000001/annual.htm | O198: -3
A199: I195 | B199: Assets | C199: 2024-12-31 | D199: USD | E199: 1300000000 | F199: available | H199: us-gaap:Assets | I199: Assets | J199: 0000000001-24-000001 | K199: 2025-02-01 | L199: https://www.sec.gov/Archives/edgar/data/1/000000000124000001/annual.htm | O199: -3
A200: I196 | B200: Consolidated equity / assets | C200: 2024-12-31 | D200: % | E200: =E198/E199 -> 0.47692308 | F200: available
A201: I197 | B201: Effective tax rate — reconciled | C201: 2021-12-31 | D201: % | E201: =E154/E157 -> 0.2 | F201: available
A202: I198 | B202: Effective tax rate — reconciled | C202: 2022-12-31 | D202: % | E202: =E161/E164 -> 0.2 | F202: available
A203: I199 | B203: Effective tax rate — reconciled | C203: 2023-12-31 | D203: % | E203: =E168/E171 -> 0.2 | F203: available
A204: I200 | B204: Effective tax rate — reconciled | C204: 2024-12-31 | D204: % | E204: =E175/E178 -> 0.2 | F204: available
A205: I201 | B205: OperatingIncomeLoss | C205: 2021-12-31 | D205: USD | E205: 80000000 | F205: available | H205: us-gaap:OperatingIncomeLoss | I205: OperatingIncomeLoss | J205: 0000000001-21-000001 | K205: 2022-02-01 | L205: https://www.sec.gov/Archives/edgar/data/1/000000000121000001/annual.htm | O205: -3
A206: I202 | B206: After-tax operating income — ETR proxy | C206: 2021-12-31 | D206: USD | E206: =E205*(1-E201) -> 64000000 | F206: available
A207: I203 | B207: OperatingIncomeLoss | C207: 2022-12-31 | D207: USD | E207: 90000000 | F207: available | H207: us-gaap:OperatingIncomeLoss | I207: OperatingIncomeLoss | J207: 0000000001-22-000001 | K207: 2023-02-01 | L207: https://www.sec.gov/Archives/edgar/data/1/000000000122000001/annual.htm | O207: -3
A208: I204 | B208: After-tax operating income — ETR proxy | C208: 2022-12-31 | D208: USD | E208: =E207*(1-E202) -> 72000000 | F208: available
A209: I205 | B209: OperatingIncomeLoss | C209: 2023-12-31 | D209: USD | E209: 100000000 | F209: available | H209: us-gaap:OperatingIncomeLoss | I209: OperatingIncomeLoss | J209: 0000000001-23-000001 | K209: 2024-02-01 | L209: https://www.sec.gov/Archives/edgar/data/1/000000000123000001/annual.htm | O209: -3
A210: I206 | B210: After-tax operating income — ETR proxy | C210: 2023-12-31 | D210: USD | E210: =E209*(1-E203) -> 80000000 | F210: available
A211: I207 | B211: OperatingIncomeLoss | C211: 2024-12-31 | D211: USD | E211: 180000000 | F211: available | H211: us-gaap:OperatingIncomeLoss | I211: OperatingIncomeLoss | J211: 0000000001-24-000001 | K211: 2025-02-01 | L211: https://www.sec.gov/Archives/edgar/data/1/000000000124000001/annual.htm | O211: -3
A212: I208 | B212: After-tax operating income — ETR proxy | C212: 2024-12-31 | D212: USD | E212: =E211*(1-E204) -> 144000000 | F212: available
A213: I209 | B213: DebtAndCapitalLeaseObligations | C213: 2021-12-31 | D213: USD | E213: 100000000 | F213: available | H213: us-gaap:DebtAndCapitalLeaseObligations | I213: DebtAndCapitalLeaseObligations | J213: 0000000001-21-000001 | K213: 2022-02-01 | L213: https://www.sec.gov/Archives/edgar/data/1/000000000121000001/annual.htm | O213: -3
A214: I210 | B214: CashAndCashEquivalentsAtCarryingValue | C214: 2021-12-31 | D214: USD | E214: 40000000 | F214: available | H214: us-gaap:CashAndCashEquivalentsAtCarryingValue | I214: CashAndCashEquivalentsAtCarryingValue | J214: 0000000001-21-000001 | K214: 2022-02-01 | L214: https://www.sec.gov/Archives/edgar/data/1/000000000121000001/annual.htm | O214: -3
A215: I211 | B215: Invested capital — cash-deducted proxy | C215: 2021-12-31 | D215: USD | E215: =E213+E189-E214 -> 470000000 | F215: available
A216: I212 | B216: DebtAndCapitalLeaseObligations | C216: 2022-12-31 | D216: USD | E216: 120000000 | F216: available | H216: us-gaap:DebtAndCapitalLeaseObligations | I216: DebtAndCapitalLeaseObligations | J216: 0000000001-22-000001 | K216: 2023-02-01 | L216: https://www.sec.gov/Archives/edgar/data/1/000000000122000001/annual.htm | O216: -3
A217: I213 | B217: CashAndCashEquivalentsAtCarryingValue | C217: 2022-12-31 | D217: USD | E217: 45000000 | F217: available | H217: us-gaap:CashAndCashEquivalentsAtCarryingValue | I217: CashAndCashEquivalentsAtCarryingValue | J217: 0000000001-22-000001 | K217: 2023-02-01 | L217: https://www.sec.gov/Archives/edgar/data/1/000000000122000001/annual.htm | O217: -3
A218: I214 | B218: Invested capital — cash-deducted proxy | C218: 2022-12-31 | D218: USD | E218: =E216+E192-E217 -> 535000000 | F218: available
A219: I215 | B219: DebtAndCapitalLeaseObligations | C219: 2023-12-31 | D219: USD | E219: 150000000 | F219: available | H219: us-gaap:DebtAndCapitalLeaseObligations | I219: DebtAndCapitalLeaseObligations | J219: 0000000001-23-000001 | K219: 2024-02-01 | L219: https://www.sec.gov/Archives/edgar/data/1/000000000123000001/annual.htm | O219: -3
A220: I216 | B220: CashAndCashEquivalentsAtCarryingValue | C220: 2023-12-31 | D220: USD | E220: 50000000 | F220: available | H220: us-gaap:CashAndCashEquivalentsAtCarryingValue | I220: CashAndCashEquivalentsAtCarryingValue | J220: 0000000001-23-000001 | K220: 2024-02-01 | L220: https://www.sec.gov/Archives/edgar/data/1/000000000123000001/annual.htm | O220: -3
A221: I217 | B221: Invested capital — cash-deducted proxy | C221: 2023-12-31 | D221: USD | E221: =E219+E195-E220 -> 610000000 | F221: available
A222: I218 | B222: DebtAndCapitalLeaseObligations | C222: 2024-12-31 | D222: USD | E222: 180000000 | F222: available | H222: us-gaap:DebtAndCapitalLeaseObligations | I222: DebtAndCapitalLeaseObligations | J222: 0000000001-24-000001 | K222: 2025-02-01 | L222: https://www.sec.gov/Archives/edgar/data/1/000000000124000001/annual.htm | O222: -3
A223: I219 | B223: CashAndCashEquivalentsAtCarryingValue | C223: 2024-12-31 | D223: USD | E223: 60000000 | F223: available | H223: us-gaap:CashAndCashEquivalentsAtCarryingValue | I223: CashAndCashEquivalentsAtCarryingValue | J223: 0000000001-24-000001 | K223: 2025-02-01 | L223: https://www.sec.gov/Archives/edgar/data/1/000000000124000001/annual.htm | O223: -3
A224: I220 | B224: Invested capital — cash-deducted proxy | C224: 2024-12-31 | D224: USD | E224: =E222+E198-E223 -> 740000000 | F224: available
A225: I221 | B225: ROIC — effective-tax, cash-deducted proxy | C225: 2021-12-31 | D225: % | F225: unavailable | G225: A consecutive opening invested-capital balance is required.
...

Sheet Revenue & Segments
A1: Historical teaching fixture | Revenue & Segments
A2: Historical only · currency in millions · missing cells carry explanations
A4: Metric / reported line | B4: 2021-12-31 | C4: 2022-12-31 | D4: 2023-12-31 | E4: 2024-12-31
A5: Revenue & Segments
A6: Revenues [USD million] | B6: ='Calculation Inputs'!E5/1000000 -> 800 | C6: ='Calculation Inputs'!E6/1000000 -> 900 | D6: ='Calculation Inputs'!E7/1000000 -> 1000 | E6: ='Calculation Inputs'!E8/1000000 -> 1200
A7: GrossProfit [USD million] | B7: ='Calculation Inputs'!E9/1000000 -> 300 | C7: ='Calculation Inputs'!E10/1000000 -> 350 | D7: ='Calculation Inputs'!E11/1000000 -> 400 | E7: ='Calculation Inputs'!E12/1000000 -> 500
A8: OperatingIncomeLoss [USD million] | B8: ='Calculation Inputs'!E13/1000000 -> 80 | C8: ='Calculation Inputs'!E14/1000000 -> 90 | D8: ='Calculation Inputs'!E15/1000000 -> 100 | E8: ='Calculation Inputs'!E16/1000000 -> 180
A9: Retail revenue · Business Segments: Retail [USD million] | D9: ='Calculation Inputs'!E19/1000000 -> 400 | E9: ='Calculation Inputs'!E20/1000000 -> 600

Sheet Working Capital
A1: Historical teaching fixture | Working Capital
A2: Historical only · currency in millions · missing cells carry explanations
A4: Metric / reported line | B4: 2021-12-31 | C4: 2022-12-31 | D4: 2023-12-31 | E4: 2024-12-31
A5: Working Capital
A6: AssetsCurrent [USD million] | B6: ='Calculation Inputs'!E21/1000000 -> 250 | C6: ='Calculation Inputs'!E22/1000000 -> 300 | D6: ='Calculation Inputs'!E23/1000000 -> 350 | E6: ='Calculation Inputs'!E24/1000000 -> 400
A7: LiabilitiesCurrent [USD million] | B7: ='Calculation Inputs'!E25/1000000 -> 100 | C7: ='Calculation Inputs'!E26/1000000 -> 120 | D7: ='Calculation Inputs'!E27/1000000 -> 140 | E7: ='Calculation Inputs'!E28/1000000 -> 160
A8: AccountsReceivableNetCurrent [USD million] | B8: ='Calculation Inputs'!E29/1000000 -> 70 | C8: ='Calculation Inputs'!E30/1000000 -> 80 | D8: ='Calculation Inputs'!E31/1000000 -> 90 | E8: ='Calculation Inputs'!E32/1000000 -> 110
A9: InventoryNet [USD million] | B9: ='Calculation Inputs'!E33/1000000 -> 100 | C9: ='Calculation Inputs'!E34/1000000 -> 110 | D9: ='Calculation Inputs'!E35/1000000 -> 120 | E9: ='Calculation Inputs'!E36/1000000 -> 160
A10: AccountsPayableCurrent [USD million] | B10: ='Calculation Inputs'!E37/1000000 -> 50 | C10: ='Calculation Inputs'!E38/1000000 -> 60 | D10: ='Calculation Inputs'!E39/1000000 -> 70 | E10: ='Calculation Inputs'!E40/1000000 -> 90

Sheet Debt & Liquidity
A1: Historical teaching fixture | Debt & Liquidity
A2: Historical only · currency in millions · missing cells carry explanations
A4: Metric / reported line | B4: 2021-12-31 | C4: 2022-12-31 | D4: 2023-12-31 | E4: 2024-12-31
A5: Debt & Liquidity
A6: InterestExpense [USD million] | B6: ='Calculation Inputs'!E41/1000000 -> 10 | C6: ='Calculation Inputs'!E42/1000000 -> 10 | D6: ='Calculation Inputs'!E43/1000000 -> 10 | E6: ='Calculation Inputs'!E44/1000000 -> 12
A7: CashAndCashEquivalentsAtCarryingValue [USD million] | B7: ='Calculation Inputs'!E45/1000000 -> 40 | C7: ='Calculation Inputs'!E46/1000000 -> 45 | D7: ='Calculation Inputs'!E47/1000000 -> 50 | E7: ='Calculation Inputs'!E48/1000000 -> 60
A8: ShortTermInvestments [USD million] | B8: ='Calculation Inputs'!E49/1000000 -> 10 | C8: ='Calculation Inputs'!E50/1000000 -> 12 | D8: ='Calculation Inputs'!E51/1000000 -> 15 | E8: ='Calculation Inputs'!E52/1000000 -> 20
A9: DebtAndCapitalLeaseObligations [USD million] | B9: ='Calculation Inputs'!E53/1000000 -> 100 | C9: ='Calculation Inputs'!E54/1000000 -> 120 | D9: ='Calculation Inputs'!E55/1000000 -> 150 | E9: ='Calculation Inputs'!E56/1000000 -> 180

Sheet Capital & PP&E
A1: Historical teaching fixture | Capital & PP&E
A2: Historical only · currency in millions · missing cells carry explanations
A4: Metric / reported line | B4: 2021-12-31 | C4: 2022-12-31 | D4: 2023-12-31 | E4: 2024-12-31
A5: Capital & PP&E
A6: PaymentsToAcquirePropertyPlantAndEquipment [USD million] | B6: ='Calculation Inputs'!E57/1000000 -> 30 | C6: ='Calculation Inputs'!E58/1000000 -> 40 | D6: ='Calculation Inputs'!E59/1000000 -> 45 | E6: ='Calculation Inputs'!E60/1000000 -> 50
A7: DepreciationDepletionAndAmortization [USD million] | B7: ='Calculation Inputs'!E61/1000000 -> 20 | C7: ='Calculation Inputs'!E62/1000000 -> 22 | D7: ='Calculation Inputs'!E63/1000000 -> 25 | E7: ='Calculation Inputs'!E64/1000000 -> 30

Sheet Earnings & Cash
A1: Historical teaching fixture | Earnings & Cash
A2: Historical only · currency in millions · missing cells carry explanations
A4: Metric / reported line | B4: 2021-12-31 | C4: 2022-12-31 | D4: 2023-12-31 | E4: 2024-12-31
A5: Earnings & Cash
A6: ProfitLoss [USD million] | B6: ='Calculation Inputs'!E65/1000000 -> 60 | C6: ='Calculation Inputs'!E66/1000000 -> 70 | D6: ='Calculation Inputs'!E67/1000000 -> 80 | E6: ='Calculation Inputs'!E68/1000000 -> 120
A7: NetIncomeLoss [USD million] | B7: ='Calculation Inputs'!E69/1000000 -> 58 | C7: ='Calculation Inputs'!E70/1000000 -> 68 | D7: ='Calculation Inputs'!E71/1000000 -> 78 | E7: ='Calculation Inputs'!E72/1000000 -> 118
A8: NetCashProvidedByUsedInOperatingActivities [USD million] | B8: ='Calculation Inputs'!E73/1000000 -> 90 | C8: ='Calculation Inputs'!E74/1000000 -> 100 | D8: ='Calculation Inputs'!E75/1000000 -> 110 | E8: ='Calculation Inputs'!E76/1000000 -> 150
A9: PaymentsToAcquirePropertyPlantAndEquipment [USD million] | B9: ='Calculation Inputs'!E77/1000000 -> 30 | C9: ='Calculation Inputs'!E78/1000000 -> 40 | D9: ='Calculation Inputs'!E79/1000000 -> 45 | E9: ='Calculation Inputs'!E80/1000000 -> 50
A10: DepreciationDepletionAndAmortization [USD million] | B10: ='Calculation Inputs'!E81/1000000 -> 20 | C10: ='Calculation Inputs'!E82/1000000 -> 22 | D10: ='Calculation Inputs'!E83/1000000 -> 25 | E10: ='Calculation Inputs'!E84/1000000 -> 30

Sheet Equity & Shares
A1: Historical teaching fixture | Equity & Shares
A2: Historical only · currency in millions · missing cells carry explanations
A4: Metric / reported line | B4: 2021-12-31 | C4: 2022-12-31 | D4: 2023-12-31 | E4: 2024-12-31
A5: Equity & Shares
A6: NetIncomeLossAvailableToCommonStockholdersBasic [USD million] | B6: ='Calculation Inputs'!E85/1000000 -> 58 | C6: ='Calculation Inputs'!E86/1000000 -> 68 | D6: ='Calculation Inputs'!E87/1000000 -> 78 | E6: ='Calculation Inputs'!E88/1000000 -> 118
A7: CommonStockDividendsPerShareDeclared [USD/shares] | B7: ='Calculation Inputs'!E89 -> 0.1 | C7: ='Calculation Inputs'!E90 -> 0.12 | D7: ='Calculation Inputs'!E91 -> 0.15 | E7: ='Calculation Inputs'!E92 -> 0.25
A8: EarningsPerShareBasic [USD/shares] | B8: ='Calculation Inputs'!E93 -> 0.58 | C8: ='Calculation Inputs'!E94 -> 0.68 | D8: ='Calculation Inputs'!E95 -> 0.78 | E8: ='Calculation Inputs'!E96 -> 1.475
A9: EarningsPerShareDiluted [USD/shares] | B9: ='Calculation Inputs'!E97 -> 0.58 | C9: ='Calculation Inputs'!E98 -> 0.68 | D9: ='Calculation Inputs'!E99 -> 0.78 | E9: ='Calculation Inputs'!E100 -> 1.475
A10: WeightedAverageNumberOfDilutedSharesOutstanding [shares] | B10: ='Calculation Inputs'!E101 -> 100000000 | C10: ='Calculation Inputs'!E102 -> 100000000 | D10: ='Calculation Inputs'!E103 -> 100000000 | E10: ='Calculation Inputs'!E104 -> 80000000
A11: CommonStockholdersEquity [USD million] | B11: ='Calculation Inputs'!E105/1000000 -> 400 | C11: ='Calculation Inputs'!E106/1000000 -> 450 | D11: ='Calculation Inputs'!E107/1000000 -> 500 | E11: ='Calculation Inputs'!E108/1000000 -> 600
A12: StockholdersEquityIncludingPortionAttributableToNoncontrollingInterest [USD million] | B12: ='Calculation Inputs'!E109/1000000 -> 410 | C12: ='Calculation Inputs'!E110/1000000 -> 460 | D12: ='Calculation Inputs'!E111/1000000 -> 510 | E12: ='Calculation Inputs'!E112/1000000 -> 620
A13: PaymentsOfDividendsCommonStock [USD million] | B13: ='Calculation Inputs'!E113/1000000 -> 10 | C13: ='Calculation Inputs'!E114/1000000 -> 12 | D13: ='Calculation Inputs'!E115/1000000 -> 15 | E13: ='Calculation Inputs'!E116/1000000 -> 20
A14: PaymentsForRepurchaseOfCommonStock [USD million] | B14: ='Calculation Inputs'!E117/1000000 -> 20 | C14: ='Calculation Inputs'!E118/1000000 -> 25 | D14: ='Calculation Inputs'!E119/1000000 -> 30 | E14: ='Calculation Inputs'!E120/1000000 -> 40

Sheet EBITDA & Capital
A1: Historical teaching fixture | EBITDA & Capital
A2: Historical only · currency in millions · missing cells carry explanations
A4: Metric / reported line | B4: 2021-12-31 | C4: 2022-12-31 | D4: 2023-12-31 | E4: 2024-12-31
A5: EBITDA & Capital
A6: ProfitLoss [USD million] | B6: ='Calculation Inputs'!E121/1000000 -> 60 | C6: ='Calculation Inputs'!E122/1000000 -> 70 | D6: ='Calculation Inputs'!E123/1000000 -> 80 | E6: ='Calculation Inputs'!E124/1000000 -> 120
A7: InterestExpense [USD million] | B7: ='Calculation Inputs'!E125/1000000 -> 10 | C7: ='Calculation Inputs'!E126/1000000 -> 10 | D7: ='Calculation Inputs'!E127/1000000 -> 10 | E7: ='Calculation Inputs'!E128/1000000 -> 12
A8: IncomeLossFromContinuingOperationsBeforeIncomeTaxesExtraordinaryItemsNoncontrollingInterest [USD million] | B8: ='Calculation Inputs'!E129/1000000 -> 75 | C8: ='Calculation Inputs'!E130/1000000 -> 87.5 | D8: ='Calculation Inputs'!E131/1000000 -> 100 | E8: ='Calculation Inputs'!E132/1000000 -> 150
A9: IncomeTaxExpenseBenefit [USD million] | B9: ='Calculation Inputs'!E133/1000000 -> 15 | C9: ='Calculation Inputs'!E134/1000000 -> 17.5 | D9: ='Calculation Inputs'!E135/1000000 -> 20 | E9: ='Calculation Inputs'!E136/1000000 -> 30
A10: CashAndCashEquivalentsAtCarryingValue [USD million] | B10: ='Calculation Inputs'!E137/1000000 -> 40 | C10: ='Calculation Inputs'!E138/1000000 -> 45 | D10: ='Calculation Inputs'!E139/1000000 -> 50 | E10: ='Calculation Inputs'!E140/1000000 -> 60
A11: DebtAndCapitalLeaseObligations [USD million] | B11: ='Calculation Inputs'!E141/1000000 -> 100 | C11: ='Calculation Inputs'!E142/1000000 -> 120 | D11: ='Calculation Inputs'!E143/1000000 -> 150 | E11: ='Calculation Inputs'!E144/1000000 -> 180
A12: StockholdersEquityIncludingPortionAttributableToNoncontrollingInterest [USD million] | B12: ='Calculation Inputs'!E145/1000000 -> 410 | C12: ='Calculation Inputs'!E146/1000000 -> 460 | D12: ='Calculation Inputs'!E147/1000000 -> 510 | E12: ='Calculation Inputs'!E148/1000000 -> 620
A13: DepreciationDepletionAndAmortization [USD million] | B13: ='Calculation Inputs'!E149/1000000 -> 20 | C13: ='Calculation Inputs'!E150/1000000 -> 22 | D13: ='Calculation Inputs'!E151/1000000 -> 25 | E13: ='Calculation Inputs'!E152/1000000 -> 30
A14: Earnings bridge
A15: EBITDA — reconciled historical definition [reported currency million] | B15: ='Calculation Inputs'!E159/1000000 -> 105 | C15: ='Calculation Inputs'!E166/1000000 -> 119.5 | D15: ='Calculation Inputs'!E173/1000000 -> 135 | E15: ='Calculation Inputs'!E180/1000000 -> 192
A16: EBITDA margin — reconciled definition [%] | B16: ='Calculation Inputs'!E182 -> 0.13125 | C16: ='Calculation Inputs'!E184 -> 0.13277778 | D16: ='Calculation Inputs'!E186 -> 0.135 | E16: ='Calculation Inputs'!E188 -> 0.16
A17: Capital efficiency
A18: Consolidated equity / assets [%] | B18: ='Calculation Inputs'!E191 -> 0.5125 | C18: ='Calculation Inputs'!E194 -> 0.51111111 | D18: ='Calculation Inputs'!E197 -> 0.46363636 | E18: ='Calculation Inputs'!E200 -> 0.47692308
A19: Effective tax rate — reconciled [%] | B19: ='Calculation Inputs'!E201 -> 0.2 | C19: ='Calculation Inputs'!E202 -> 0.2 | D19: ='Calculation Inputs'!E203 -> 0.2 | E19: ='Calculation Inputs'!E204 -> 0.2
A20: After-tax operating income — ETR proxy [reported currency million] | B20: ='Calculation Inputs'!E206/1000000 -> 64 | C20: ='Calculation Inputs'!E208/1000000 -> 72 | D20: ='Calculation Inputs'!E210/1000000 -> 80 | E20: ='Calculation Inputs'!E212/1000000 -> 144
A21: Invested capital — cash-deducted proxy [reported currency million] | B21: ='Calculation Inputs'!E215/1000000 -> 470 | C21: ='Calculation Inputs'!E218/1000000 -> 535 | D21: ='Calculation Inputs'!E221/1000000 -> 610 | E21: ='Calculation Inputs'!E224/1000000 -> 740
A22: ROIC — effective-tax, cash-deducted proxy [%] | C22: ='Calculation Inputs'!E227 -> 0.14328358 | D22: ='Calculation Inputs'!E229 -> 0.13973799 | E22: ='Calculation Inputs'!E231 -> 0.21333333

Sheet Operating KPIs
A1: Historical teaching fixture | Operating KPIs
A2: Historical only · currency in millions · missing cells carry explanations
A4: Metric / reported line | B4: 2021-12-31 | C4: 2022-12-31 | D4: 2023-12-31 | E4: 2024-12-31
A5: Operating KPIs
A6: Active accounts · note disclosure [pure] | D6: ='Calculation Inputs'!E234 -> 10 | E6: ='Calculation Inputs'!E235 -> 12

Sheet Historical Ratios
A1: Historical teaching fixture | Historical Ratios
A2: Historical only · currency in millions · missing cells carry explanations
A4: Metric / reported line | B4: 2021-12-31 | C4: 2022-12-31 | D4: 2023-12-31 | E4: 2024-12-31
A5: Growth
A6: Revenue growth [%] | C6: ='Calculation Inputs'!E237 -> 0.125 | D6: ='Calculation Inputs'!E238 -> 0.11111111 | E6: ='Calculation Inputs'!E239 -> 0.2
A7: Revenue CAGR — 3 annual intervals [%] | E7: ='Calculation Inputs'!E243 -> 0.14471424
A8: Profitability
A9: Gross margin [%] | B9: ='Calculation Inputs'!E245 -> 0.375 | C9: ='Calculation Inputs'!E247 -> 0.38888889 | D9: ='Calculation Inputs'!E249 -> 0.4 | E9: ='Calculation Inputs'!E251 -> 0.41666667
A10: Operating margin [%] | B10: ='Calculation Inputs'!E252 -> 0.1 | C10: ='Calculation Inputs'!E253 -> 0.1 | D10: ='Calculation Inputs'!E254 -> 0.1 | E10: ='Calculation Inputs'!E255 -> 0.15
A11: Parent net margin [%] | B11: ='Calculation Inputs'!E257 -> 0.0725 | C11: ='Calculation Inputs'!E259 -> 0.075555556 | D11: ='Calculation Inputs'!E261 -> 0.078 | E11: ='Calculation Inputs'!E263 -> 0.098333333
A12: SG&A / revenue [%]
A13: R&D / revenue [%]
A14: Capital investment
A15: PP&E purchases / revenue [%] | B15: ='Calculation Inputs'!E281 -> 0.0375 | C15: ='Calculation Inputs'!E283 -> 0.044444444 | D15: ='Calculation Inputs'!E285 -> 0.045 | E15: ='Calculation Inputs'!E287 -> 0.041666667
A16: Returns
A17: Return on assets — consolidated [%] | C17: ='Calculation Inputs'!E291 -> 0.082352941 | D17: ='Calculation Inputs'!E293 -> 0.08 | E17: ='Calculation Inputs'!E295 -> 0.1
A18: Return on common equity [%] | C18: ='Calculation Inputs'!E303 -> 0.16 | D18: ='Calculation Inputs'!E307 -> 0.16421053 | E18: ='Calculation Inputs'!E311 -> 0.21454545
A19: Liquidity
A20: Current ratio [x] | B20: ='Calculation Inputs'!E314 -> 2.5 | C20: ='Calculation Inputs'!E317 -> 2.5 | D20: ='Calculation Inputs'!E320 -> 2.5 | E20: ='Calculation Inputs'!E323 -> 2.5
A21: Quick ratio — strict components [x] | B21: ='Calculation Inputs'!E326 -> 1.2 | C21: ='Calculation Inputs'!E329 -> 1.1416667 | D21: ='Calculation Inputs'!E332 -> 1.1071429 | E21: ='Calculation Inputs'!E335 -> 1.1875
A22: Debt
A23: Reported debt incl. finance leases less cash [reported currency million] | B23: ='Calculation Inputs'!E336/1000000 -> 60 | C23: ='Calculation Inputs'!E337/1000000 -> 75 | D23: ='Calculation Inputs'!E338/1000000 -> 100 | E23: ='Calculation Inputs'!E339/1000000 -> 120
A24: Reported debt incl. finance leases / assets [%] | B24: ='Calculation Inputs'!E340 -> 0.125 | C24: ='Calculation Inputs'!E341 -> 0.13333333 | D24: ='Calculation Inputs'!E342 -> 0.13636364 | E24: ='Calculation Inputs'!E343 -> 0.13846154
A25: Operating income / interest expense [x] | B25: ='Calculation Inputs'!E344 -> 8 | C25: ='Calculation Inputs'!E345 -> 9 | D25: ='Calculation Inputs'!E346 -> 10 | E25: ='Calculation Inputs'!E347 -> 15
A26: Working capital
A27: Receivable days — sales proxy [days] | C27: ='Calculation Inputs'!E353 -> 30.416667 | D27: ='Calculation Inputs'!E356 -> 31.025 | E27: ='Calculation Inputs'!E359 -> 30.5
A28: Inventory days [days] | C28: ='Calculation Inputs'!E369 -> 69.681818 | D28: ='Calculation Inputs'!E374 -> 69.958333 | E28: ='Calculation Inputs'!E379 -> 73.2
A29: Payable days — cost-of-sales proxy [days] | C29: ='Calculation Inputs'!E387 -> 36.5 | D29: ='Calculation Inputs'!E391 -> 39.541667 | E29: ='Calculation Inputs'!E395 -> 41.828571
A30: Cash conversion cycle — proxy [days] | C30: ='Calculation Inputs'!E397 -> 63.598485 | D30: ='Calculation Inputs'!E398 -> 61.441667 | E30: ='Calculation Inputs'!E399 -> 61.871429
A31: Cash generation
A32: Operating cash flow / revenue [%] | B32: ='Calculation Inputs'!E401 -> 0.1125 | C32: ='Calculation Inputs'!E403 -> 0.11111111 | D32: ='Calculation Inputs'!E405 -> 0.11 | E32: ='Calculation Inputs'!E407 -> 0.125
A33: Operating cash flow / earnings [x] | B33: ='Calculation Inputs'!E408 -> 1.5 | C33: ='Calculation Inputs'!E409 -> 1.4285714 | D33: ='Calculation Inputs'!E410 -> 1.375 | E33: ='Calculation Inputs'!E411 -> 1.25
A34: Operating cash flow less PP&E purchases [reported currency million] | B34: ='Calculation Inputs'!E412/1000000 -> 60 | C34: ='Calculation Inputs'!E413/1000000 -> 60 | D34: ='Calculation Inputs'!E414/1000000 -> 65 | E34: ='Calculation Inputs'!E415/1000000 -> 100
A35: Earnings and cash
A36: Earnings less operating cash flow [reported currency million] | B36: ='Calculation Inputs'!E416/1000000 -> -30 | C36: ='Calculation Inputs'!E417/1000000 -> -30 | D36: ='Calculation Inputs'!E418/1000000 -> -30 | E36: ='Calculation Inputs'!E419/1000000 -> -30
A37: Earnings–cash difference / average assets [%] | C37: ='Calculation Inputs'!E423 -> -0.035294118 | D37: ='Calculation Inputs'!E425 -> -0.03 | E37: ='Calculation Inputs'!E427 -> -0.025
A38: Earnings bridge
A39: EBITDA — reconciled historical definition [reported currency million] | B39: ='Calculation Inputs'!E159/1000000 -> 105 | C39: ='Calculation Inputs'!E166/1000000 -> 119.5 | D39: ='Calculation Inputs'!E173/1000000 -> 135 | E39: ='Calculation Inputs'!E180/1000000 -> 192
A40: EBITDA margin — reconciled definition [%] | B40: ='Calculation Inputs'!E182 -> 0.13125 | C40: ='Calculation Inputs'!E184 -> 0.13277778 | D40: ='Calculation Inputs'!E186 -> 0.135 | E40: ='Calculation Inputs'!E188 -> 0.16
A41: Debt
A42: Reported debt incl. finance leases / EBITDA [x] | B42: ='Calculation Inputs'!E428 -> 0.95238095 | C42: ='Calculation Inputs'!E429 -> 1.0041841 | D42: ='Calculation Inputs'!E430 -> 1.1111111 | E42: ='Calculation Inputs'!E431 -> 0.9375
A43: EBITDA / interest expense [x] | B43: ='Calculation Inputs'!E432 -> 10.5 | C43: ='Calculation Inputs'!E433 -> 11.95 | D43: ='Calculation Inputs'!E434 -> 13.5 | E43: ='Calculation Inputs'!E435 -> 16
A44: Debt / capital — including NCI [%] | B44: ='Calculation Inputs'!E437 -> 0.19607843 | C44: ='Calculation Inputs'!E439 -> 0.20689655 | D44: ='Calculation Inputs'!E441 -> 0.22727273 | E44: ='Calculation Inputs'!E443 -> 0.225
A45: Capital efficiency
A46: Consolidated equity / assets [%] | B46: ='Calculation Inputs'!E191 -> 0.5125 | C46: ='Calculation Inputs'!E194 -> 0.51111111 | D46: ='Calculation Inputs'!E197 -> 0.46363636 | E46: ='Calculation Inputs'!E200 -> 0.47692308
A47: Effective tax rate — reconciled [%] | B47: ='Calculation Inputs'!E201 -> 0.2 | C47: ='Calculation Inputs'!E202 -> 0.2 | D47: ='Calculation Inputs'!E203 -> 0.2 | E47: ='Calculation Inputs'!E204 -> 0.2
A48: After-tax operating income — ETR proxy [reported currency million] | B48: ='Calculation Inputs'!E206/1000000 -> 64 | C48: ='Calculation Inputs'!E208/1000000 -> 72 | D48: ='Calculation Inputs'!E210/1000000 -> 80 | E48: ='Calculation Inputs'!E212/1000000 -> 144
A49: Invested capital — cash-deducted proxy [reported currency million] | B49: ='Calculation Inputs'!E215/1000000 -> 470 | C49: ='Calculation Inputs'!E218/1000000 -> 535 | D49: ='Calculation Inputs'!E221/1000000 -> 610 | E49: ='Calculation Inputs'!E224/1000000 -> 740
A50: ROIC — effective-tax, cash-deducted proxy [%] | C50: ='Calculation Inputs'!E227 -> 0.14328358 | D50: ='Calculation Inputs'!E229 -> 0.13973799 | E50: ='Calculation Inputs'!E231 -> 0.21333333
A51: Shareholder analysis
A52: Parent earnings growth [%] | C52: ='Calculation Inputs'!E445 -> 0.17241379 | D52: ='Calculation Inputs'!E446 -> 0.14705882 | E52: ='Calculation Inputs'!E447 -> 0.51282051
A53: Common earnings growth — same filing [%] | E53: ='Calculation Inputs'!E454 -> 0.51282051
A54: Diluted EPS growth — same filing [%] | E54: ='Calculation Inputs'!E465 -> 0.89102564
A55: Diluted weighted shares change — same filing [%] | E55: ='Calculation Inputs'!E476 -> -0.2
A56: EPS versus common-earnings growth gap [pp] | E56: ='Calculation Inputs'!E480*100 -> 37.820513
A57: Cash common-dividend payout [%] | B57: ='Calculation Inputs'!E482 -> 0.17241379 | C57: ='Calculation Inputs'!E484 -> 0.17647059 | D57: ='Calculation Inputs'!E486 -> 0.19230769 | E57: ='Calculation Inputs'!E488 -> 0.16949153
A58: Declared common DPS / basic EPS [%] | B58: ='Calculation Inputs'!E491 -> 0.17241379 | C58: ='Calculation Inputs'!E494 -> 0.17647059 | D58: ='Calculation Inputs'!E497 -> 0.19230769 | E58: ='Calculation Inputs'!E500 -> 0.16949153
A59: Common repurchase cash / common earnings [%] | B59: ='Calculation Inputs'!E502 -> 0.34482759 | C59: ='Calculation Inputs'!E504 -> 0.36764706 | D59: ='Calculation Inputs'!E506 -> 0.38461538 | E59: ='Calculation Inputs'!E508 -> 0.33898305
A60: Cash returned to common shareholders [reported currency million] | B60: ='Calculation Inputs'!E509/1000000 -> 30 | C60: ='Calculation Inputs'!E510/1000000 -> 37 | D60: ='Calculation Inputs'!E511/1000000 -> 45 | E60: ='Calculation Inputs'!E512/1000000 -> 60
A61: Profitability
A62: Gross margin change [pp] | C62: ='Calculation Inputs'!E514*100 -> 1.3888889 | D62: ='Calculation Inputs'!E515*100 -> 1.1111111 | E62: ='Calculation Inputs'!E516*100 -> 1.6666667
A63: Operating margin change [pp] | C63: ='Calculation Inputs'!E518*100 -> 0 | D63: ='Calculation Inputs'!E519*100 -> 0 | E63: ='Calculation Inputs'!E520*100 -> 5
A64: Parent net margin change [pp] | C64: ='Calculation Inputs'!E522*100 -> 0.30555556 | D64: ='Calculation Inputs'!E523*100 -> 0.24444444 | E64: ='Calculation Inputs'!E524*100 -> 2.0333333
A65: Business drivers
A66: Retail revenue · Business Segments: Retail — annual growth [%] | E66: ='Calculation Inputs'!E532 -> 0.5
A67: Retail revenue · Business Segments: Retail — revenue share [%] | E67: ='Calculation Inputs'!E536 -> 0.5
A68: Active accounts · note disclosure — annual growth [%] | E68: ='Calculation Inputs'!E544 -> 0.2

Sheet Return Bridge
A1: Historical teaching fixture | Return Bridge
A2: Historical only · currency in millions · missing cells carry explanations
A4: Metric / reported line | B4: 2021-12-31 | C4: 2022-12-31 | D4: 2023-12-31 | E4: 2024-12-31
A5: Return bridge
A6: Asset turnover — total assets [x] | C6: ='Calculation Inputs'!E548 -> 1.0588235 | D6: ='Calculation Inputs'!E550 -> 1 | E6: ='Calculation Inputs'!E552 -> 1
A7: Operating return on total assets [%] | C7: ='Calculation Inputs'!E556 -> 0.10588235 | D7: ='Calculation Inputs'!E558 -> 0.1 | E7: ='Calculation Inputs'!E560 -> 0.15
A8: Change in operating return [pp] | D8: ='Calculation Inputs'!E563*100 -> -0.58823529 | E8: ='Calculation Inputs'!E564*100 -> 5
A9: Margin-change contribution [pp] | D9: ='Calculation Inputs'!E567*100 -> 0 | E9: ='Calculation Inputs'!E568*100 -> 5
A10: Turnover-change contribution [pp] | D10: ='Calculation Inputs'!E571*100 -> -0.58823529 | E10: ='Calculation Inputs'!E572*100 -> 0
A11: Margin/turnover interaction [pp] | D11: ='Calculation Inputs'!E575*100 -> 0 | E11: ='Calculation Inputs'!E576*100 -> 0

Sheet Common Size
A1: Historical teaching fixture | Common Size
A2: Historical only · currency in millions · missing cells carry explanations
A4: Metric / reported line | B4: 2021-12-31 | C4: 2022-12-31 | D4: 2023-12-31 | E4: 2024-12-31
A5: Profit & Loss
A6: Revenues [%] | B6: ='Calculation Inputs'!E578 -> 1 | C6: ='Calculation Inputs'!E580 -> 1 | D6: ='Calculation Inputs'!E582 -> 1 | E6: ='Calculation Inputs'!E584 -> 1
A7: CostOfRevenue [%] | B7: ='Calculation Inputs'!E586 -> 0.625 | C7: ='Calculation Inputs'!E588 -> 0.61111111 | D7: ='Calculation Inputs'!E590 -> 0.6 | E7: ='Calculation Inputs'!E592 -> 0.58333333
A8: GrossProfit [%] | B8: ='Calculation Inputs'!E594 -> 0.375 | C8: ='Calculation Inputs'!E596 -> 0.38888889 | D8: ='Calculation Inputs'!E598 -> 0.4 | E8: ='Calculation Inputs'!E600 -> 0.41666667
A9: OperatingIncomeLoss [%] | B9: ='Calculation Inputs'!E602 -> 0.1 | C9: ='Calculation Inputs'!E604 -> 0.1 | D9: ='Calculation Inputs'!E606 -> 0.1 | E9: ='Calculation Inputs'!E608 -> 0.15
A10: ProfitLoss [%] | B10: ='Calculation Inputs'!E610 -> 0.075 | C10: ='Calculation Inputs'!E612 -> 0.077777778 | D10: ='Calculation Inputs'!E614 -> 0.08 | E10: ='Calculation Inputs'!E616 -> 0.1
A11: NetIncomeLoss [%] | B11: ='Calculation Inputs'!E618 -> 0.0725 | C11: ='Calculation Inputs'!E620 -> 0.075555556 | D11: ='Calculation Inputs'!E622 -> 0.078 | E11: ='Calculation Inputs'!E624 -> 0.098333333
A12: NetIncomeLossAvailableToCommonStockholdersBasic [%] | B12: ='Calculation Inputs'!E626 -> 0.0725 | C12: ='Calculation Inputs'!E628 -> 0.075555556 | D12: ='Calculation Inputs'!E630 -> 0.078 | E12: ='Calculation Inputs'!E632 -> 0.098333333
A13: InterestExpense [%] | B13: ='Calculation Inputs'!E634 -> 0.0125 | C13: ='Calculation Inputs'!E636 -> 0.011111111 | D13: ='Calculation Inputs'!E638 -> 0.01 | E13: ='Calculation Inputs'!E640 -> 0.01
A14: IncomeLossFromContinuingOperationsBeforeIncomeTaxesExtraordinaryItemsNoncontrollingInterest [%] | B14: ='Calculation Inputs'!E642 -> 0.09375 | C14: ='Calculation Inputs'!E644 -> 0.097222222 | D14: ='Calculation Inputs'!E646 -> 0.1 | E14: ='Calculation Inputs'!E648 -> 0.125
A15: IncomeTaxExpenseBenefit [%] | B15: ='Calculation Inputs'!E650 -> 0.01875 | C15: ='Calculation Inputs'!E652 -> 0.019444444 | D15: ='Calculation Inputs'!E654 -> 0.02 | E15: ='Calculation Inputs'!E656 -> 0.025
A16: Balance Sheet
A17: Assets [%] | B17: ='Calculation Inputs'!E658 -> 1 | C17: ='Calculation Inputs'!E660 -> 1 | D17: ='Calculation Inputs'!E662 -> 1 | E17: ='Calculation Inputs'!E664 -> 1
A18: LiabilitiesAndStockholdersEquity [%] | B18: ='Calculation Inputs'!E666 -> 1 | C18: ='Calculation Inputs'!E668 -> 1 | D18: ='Calculation Inputs'!E670 -> 1 | E18: ='Calculation Inputs'!E672 -> 1
A19: AssetsCurrent [%] | B19: ='Calculation Inputs'!E674 -> 0.3125 | C19: ='Calculation Inputs'!E676 -> 0.33333333 | D19: ='Calculation Inputs'!E678 -> 0.31818182 | E19: ='Calculation Inputs'!E680 -> 0.30769231
A20: LiabilitiesCurrent [%] | B20: ='Calculation Inputs'!E682 -> 0.125 | C20: ='Calculation Inputs'!E684 -> 0.13333333 | D20: ='Calculation Inputs'!E686 -> 0.12727273 | E20: ='Calculation Inputs'!E688 -> 0.12307692
A21: CashAndCashEquivalentsAtCarryingValue [%] | B21: ='Calculation Inputs'!E690 -> 0.05 | C21: ='Calculation Inputs'!E692 -> 0.05 | D21: ='Calculation Inputs'!E694 -> 0.045454545 | E21: ='Calculation Inputs'!E696 -> 0.046153846
A22: ShortTermInvestments [%] | B22: ='Calculation Inputs'!E698 -> 0.0125 | C22: ='Calculation Inputs'!E700 -> 0.013333333 | D22: ='Calculation Inputs'!E702 -> 0.013636364 | E22: ='Calculation Inputs'!E704 -> 0.015384615
A23: AccountsReceivableNetCurrent [%] | B23: ='Calculation Inputs'!E706 -> 0.0875 | C23: ='Calculation Inputs'!E708 -> 0.088888889 | D23: ='Calculation Inputs'!E710 -> 0.081818182 | E23: ='Calculation Inputs'!E712 -> 0.084615385
A24: InventoryNet [%] | B24: ='Calculation Inputs'!E714 -> 0.125 | C24: ='Calculation Inputs'!E716 -> 0.12222222 | D24: ='Calculation Inputs'!E718 -> 0.10909091 | E24: ='Calculation Inputs'!E720 -> 0.12307692
A25: AccountsPayableCurrent [%] | B25: ='Calculation Inputs'!E722 -> 0.0625 | C25: ='Calculation Inputs'!E724 -> 0.066666667 | D25: ='Calculation Inputs'!E726 -> 0.063636364 | E25: ='Calculation Inputs'!E728 -> 0.069230769
A26: CommonStockholdersEquity [%] | B26: ='Calculation Inputs'!E730 -> 0.5 | C26: ='Calculation Inputs'!E732 -> 0.5 | D26: ='Calculation Inputs'!E734 -> 0.45454545 | E26: ='Calculation Inputs'!E736 -> 0.46153846
A27: DebtAndCapitalLeaseObligations [%] | B27: ='Calculation Inputs'!E738 -> 0.125 | C27: ='Calculation Inputs'!E740 -> 0.13333333 | D27: ='Calculation Inputs'!E742 -> 0.13636364 | E27: ='Calculation Inputs'!E744 -> 0.13846154
A28: StockholdersEquityIncludingPortionAttributableToNoncontrollingInterest [%] | B28: ='Calculation Inputs'!E746 -> 0.5125 | C28: ='Calculation Inputs'!E748 -> 0.51111111 | D28: ='Calculation Inputs'!E750 -> 0.46363636 | E28: ='Calculation Inputs'!E752 -> 0.47692308

Sheet Business Drivers
A1: Historical teaching fixture | Business Drivers
A2: Historical only · currency in millions · missing cells carry explanations
A4: Metric / reported line | B4: 2021-12-31 | C4: 2022-12-31 | D4: 2023-12-31 | E4: 2024-12-31
A5: Business drivers
A6: Retail revenue · Business Segments: Retail — annual growth [%] | E6: ='Calculation Inputs'!E532 -> 0.5
A7: Retail revenue · Business Segments: Retail — revenue share [%] | E7: ='Calculation Inputs'!E536 -> 0.5
A8: Active accounts · note disclosure — annual growth [%] | E8: ='Calculation Inputs'!E544 -> 0.2

Sheet Methodology
A1: Historical teaching fixture | Methodology
A2: Fishtorian · historical methods and interpretation
A4: Metric | B4: Group | C4: Formula | D4: Unit | E4: Purpose | F4: Applicability | G4: Balance convention | H4: Limitations | I4: Reference
A5: Revenue growth | B5: Growth | C5: Revenue / prior equivalent revenue − 1 | D5: % | E5: Change in the selected revenue basis over one fiscal year. | F5: Where required compatible inputs exist | G5: Two-point beginning/ending average where formula specifies average; consecutive annual periods | H5: An acquisition or change in revenue definition can prevent like-for-like comparison. | I5: Historical ratio convention; product definition.
A6: Revenue CAGR — 3 annual intervals | B6: Growth | C6: (Revenue / revenue 3 annual intervals earlier)^(1/3) − 1 | D6: % | E6: Annualized historical change between positive endpoints. | F6: Where required compatible inputs exist | G6: Two-point beginning/ending average where formula specifies average; consecutive annual periods | H6: Requires four consecutive observations of equivalent scope; smooths intervening changes. | I6: Historical ratio convention; product definition.
A7: Gross margin | B7: Profitability | C7: Gross profit / matching sales | D7: % | E7: Share of sales remaining after reported cost of sales. | F7: Known nonfinancial SEC SIC | G7: Two-point beginning/ending average where formula specifies average; consecutive annual periods | H7: Only calculated when the sales/cost/gross-profit relationship reconciles; industries differ. | I7: Historical ratio convention; product definition.
A8: Operating margin | B8: Profitability | C8: Operating income / selected revenue | D8: % | E8: Reported operating income per unit of revenue. | F8: Known nonfinancial SEC SIC | G8: Two-point beginning/ending average where formula specifies average; consecutive annual periods | H8: Reported classifications and unusual charges affect comparison. | I8: Historical ratio convention; product definition.
A9: Parent net margin | B9: Profitability | C9: Parent net income / selected revenue | D9: % | E9: Parent earnings relative to revenue. | F9: Where required compatible inputs exist | G9: Two-point beginning/ending average where formula specifies average; consecutive annual periods | H9: Parent earnings and consolidated revenue have different ownership scope; this is labelled explicitly. | I9: Historical ratio convention; product definition.
A10: SG&A / revenue | B10: Profitability | C10: SG&A / selected revenue | D10: % | E10: Reported selling, general and administrative expense relative to revenue. | F10: Known nonfinancial SEC SIC | G10: Two-point beginning/ending average where formula specifies average; consecutive annual periods | H10: Some issuers include costs that others report separately. | I10: Historical ratio convention; product definition.
A11: R&D / revenue | B11: Profitability | C11: R&D / selected revenue | D11: % | E11: Reported research and development expense relative to revenue. | F11: Known nonfinancial SEC SIC | G11: Two-point beginning/ending average where formula specifies average; consecutive annual periods | H11: Capitalized development costs are not inferred. | I11: Historical ratio convention; product definition.
A12: PP&E purchases / revenue | B12: Capital investment | C12: ABS(PP&E purchases) / selected revenue | D12: % | E12: Cash investment in PP&E relative to revenue. | F12: Known nonfinancial SEC SIC | G12: Two-point beginning/ending average where formula specifies average; consecutive annual periods | H12: Acquisitions, noncash additions and other productive assets are not included. | I12: Historical ratio convention; product definition.
A13: Return on assets — consolidated | B13: Returns | C13: Consolidated net income / average total assets | D13: % | E13: Consolidated earnings relative to assets employed. | F13: Where required compatible inputs exist | G13: Two-point beginning/ending average where formula specifies average; consecutive annual periods | H13: Average uses two year-end balances; acquisitions can distort the comparison. | I13: Historical ratio convention; product definition.
A14: Return on common equity | B14: Returns | C14: Common-shareholder income / average common equity | D14: % | E14: Common-shareholder earnings relative to common equity. | F14: Where required compatible inputs exist | G14: Two-point beginning/ending average where formula specifies average; consecutive annual periods | H14: Requires explicit common income and equity; parent equity is not assumed to exclude preferred equity. | I14: Historical ratio convention; product definition.
A15: Current ratio | B15: Liquidity | C15: Current assets / current liabilities | D15: x | E15: Relationship between reported short-term assets and obligations. | F15: Known nonfinancial SEC SIC | G15: Two-point beginning/ending average where formula specifies average; consecutive annual periods | H15: It does not measure the timing or realizability of individual assets. | I15: Historical ratio convention; product definition.
... A59: Active accounts · note disclosure — annual growth | B59: Business drivers | C59: Current / same-filing prior − 1 | D59: % | E59: Reviewed KPI: active accounts at fiscal end, not unique people. | F59: Where required compatible inputs exist | G59: Two-point beginning/ending average where formula specifies average; consecutive annual periods | H59: Same exact tag, member and unit; no inferred unique users or recurring revenue. | I59: Historical ratio convention; product definition.
A61: Policy | C61: Historical calculations only. No forecast, valuation, recommendation or CFA certification.
A62: Policy | C62: Revenue basis is selected in order: total revenue, net sales, customer-contract revenue. Growth requires unchanged scope. Inspect every calculation's inputs.
A63: Policy | C63: Cash-flow movements and balance-sheet changes are different measures. Schedule groupings do not imply complete roll-forwards.
A64: Policy | C64: Advanced NOA/NFO and after-tax RNOA are unavailable without complete operating/financing classifications and tax allocations; no assumptions are inserted.
A65: Policy | C65: ROIC is a labelled historical proxy using the reported effective tax rate and debt + consolidated equity − all cash; it is not operating-tax allocation, Morningstar ROIC or NOA/RNOA.
A66: Policy | C66: EBITDA requires consolidated NI + tax to reconcile to continuing pretax income. No SBC or exceptional-item addbacks. EBITDA is not cash flow or covenant EBITDA.
A67: Policy | C67: Per-share and business-driver growth require same-filing comparatives; missing split or segment-definition evidence is not guessed.
A68: Policy | C68: Operating KPIs require reviewed company-specific mappings. No subscriber, active-device or user counts are inferred from revenue or report prose.
A69: Policy | C69: Peer comparability scoring is not implemented. The De Franco measure needs a separate quarterly earnings/return design.
A70: Policy | C70: Institutional acceptance pending independent live-filing verification across representative companies; passed checks are not an audit.

Sheet Validation
A1: Historical teaching fixture | Validation
A2: Passed checks are not a financial audit; unavailable checks remain explicit
A4: Period | B4: Check | C4: Status | D4: Difference | E4: Tolerance | F4: Explanation
A5: 2021-12-31 | B5: NI plus tax versus continuing pretax income | C5: passed | D5: 0 | E5: 1500 | F5: Checked compatible selected inputs with explicit rounding tolerance; not an audit.
A6: 2021-12-31 | B6: Assets versus reported liabilities and equity | C6: passed | D6: 0 | E6: 1000 | F6: Checked compatible selected inputs with explicit rounding tolerance; not an audit.
A7: 2021-12-31 | B7: Cash movement — cash equivalents | C7: insufficient information | F7: cash end: Required reported input is unavailable or unsupported. cash begin: Required reported input is unavailable or unsupported. cash change: Required reported input is unavailable or unsupported.
A8: 2021-12-31 | B8: Cash movement — including restricted cash | C8: insufficient information | F8: restricted cash end: Required reported input is unavailable or unsupported. restricted cash begin: Required reported input is unavailable or unsupported. restricted cash change: Required reported input is unavailable or unsupported.
A9: 2021-12-31 | B9: Operating return bridge | C9: insufficient information | F9: Change in operating return: Prior annual return inputs are unavailable. Margin-change contribution: Prior annual return inputs are unavailable. Turnover-change contribution: Prior annual return inputs are unavailable. Margin/turnover interaction: Prior annual return inputs are unavailable.
A10: 2022-12-31 | B10: NI plus tax versus continuing pretax income | C10: passed | D10: 0 | E10: 1500 | F10: Checked compatible selected inputs with explicit rounding tolerance; not an audit.
A11: 2022-12-31 | B11: Assets versus reported liabilities and equity | C11: passed | D11: 0 | E11: 1000 | F11: Checked compatible selected inputs with explicit rounding tolerance; not an audit.
A12: 2022-12-31 | B12: Cash movement — cash equivalents | C12: insufficient information | F12: cash end: Required reported input is unavailable or unsupported. cash begin: Required reported input is unavailable or unsupported. cash change: Required reported input is unavailable or unsupported.
A13: 2022-12-31 | B13: Cash movement — including restricted cash | C13: insufficient information | F13: restricted cash end: Required reported input is unavailable or unsupported. restricted cash begin: Required reported input is unavailable or unsupported. restricted cash change: Required reported input is unavailable or unsupported.
A14: 2022-12-31 | B14: Operating return bridge | C14: insufficient information | F14: Change in operating return: Operating return on total assets: Average assets: Consecutive beginning balance is unavailable. Margin-change contribution: Asset turnover — total assets: Average assets: Consecutive beginning balance is unavailable. Turnover-change contribution: Asset turnover — total assets: Average assets: Consecutive beginning balance is unavailable. Margin/turnover interaction: Asset turnover — total assets: Average assets: Consecutive beginning balance is unavailable.
A15: 2023-12-31 | B15: NI plus tax versus continuing pretax income | C15: passed | D15: 0 | E15: 1500 | F15: Checked compatible selected inputs with explicit rounding tolerance; not an audit.
A16: 2023-12-31 | B16: Assets versus reported liabilities and equity | C16: passed | D16: 0 | E16: 1000 | F16: Checked compatible selected inputs with explicit rounding tolerance; not an audit.
A17: 2023-12-31 | B17: Cash movement — cash equivalents | C17: insufficient information | F17: cash end: Required reported input is unavailable or unsupported. cash begin: Required reported input is unavailable or unsupported. cash change: Required reported input is unavailable or unsupported.
A18: 2023-12-31 | B18: Cash movement — including restricted cash | C18: insufficient information | F18: restricted cash end: Required reported input is unavailable or unsupported. restricted cash begin: Required reported input is unavailable or unsupported. restricted cash change: Required reported input is unavailable or unsupported.
A19: 2023-12-31 | B19: Operating return bridge | C19: passed | D19: 0 | E19: 1e-09 | F19: Checked compatible selected inputs with explicit rounding tolerance; not an audit.
A20: 2024-12-31 | B20: NI plus tax versus continuing pretax income | C20: passed | D20: 0 | E20: 1500 | F20: Checked compatible selected inputs with explicit rounding tolerance; not an audit.
A21: 2024-12-31 | B21: Assets versus reported liabilities and equity | C21: passed | D21: 0 | E21: 1000 | F21: Checked compatible selected inputs with explicit rounding tolerance; not an audit.
A22: 2024-12-31 | B22: Cash movement — cash equivalents | C22: insufficient information | F22: cash end: Required reported input is unavailable or unsupported. cash begin: Required reported input is unavailable or unsupported. cash change: Required reported input is unavailable or unsupported.
A23: 2024-12-31 | B23: Cash movement — including restricted cash | C23: insufficient information | F23: restricted cash end: Required reported input is unavailable or unsupported. restricted cash begin: Required reported input is unavailable or unsupported. restricted cash change: Required reported input is unavailable or unsupported.
A24: 2024-12-31 | B24: Operating return bridge | C24: passed | D24: 0 | E24: 1e-09 | F24: Checked compatible selected inputs with explicit rounding tolerance; not an audit.
